{"Position":"LJ","bb":25,"Fold":{"AA": [0.0, -0.2], "A2s": [0.0, -0.2], "A2o": [0.0, -0.2], "A3s": [0.0, -0.2], "A3o": [0.0, -0.2], "A4s": [0.0, -0.2], "A4o": [0.0, -0.2], "A5s": [0.336, -0.2], "A5o": [0.0, -0.2], "A6s": [0.0, -0.2], "A6o": [0.0, -0.2], "A7s": [0.0, -0.2], "A7o": [0.0, -0.2], "A8s": [0.609, -0.2], "A8o": [0.0, -0.2], "A9s": [0.0, -0.2], "A9o": [0.0, -0.2], "ATs": [0.0, -0.2], "ATo": [0.516, -0.2], "AJs": [0.0, -0.2], "AJo": [0.606, -0.2], "AQs": [0.348, -0.2], "AQo": [0.192, -0.2], "AKs": [0.896, -0.2], "AKo": [0.951, -0.2], "22": [0.0, -0.2], "32s": [0.0, -0.2], "32o": [0.0, -0.2], "42s": [0.0, -0.2], "42o": [0.0, -0.2], "52s": [0.0, -0.2], "52o": [0.0, -0.2], "62s": [0.0, -0.2], "62o": [0.0, -0.2], "72s": [0.0, -0.2], "72o": [0.0, -0.2], "82s": [0.0, -0.2], "82o": [0.0, -0.2], "92s": [0.0, -0.2], "92o": [0.0, -0.2], "T2s": [0.0, -0.2], "T2o": [0.0, -0.2], "J2s": [0.0, -0.2], "J2o": [0.0, -0.2], "Q2s": [0.0, -0.2], "Q2o": [0.0, -0.2], "K2s": [0.0, -0.2], "K2o": [0.0, -0.2], "33": [0.0, -0.2], "43s": [0.0, -0.2], "43o": [0.0, -0.2], "53s": [0.0, -0.2], "53o": [0.0, -0.2], "63s": [0.0, -0.2], "63o": [0.0, -0.2], "73s": [0.0, -0.2], "73o": [0.0, -0.2], "83s": [0.0, -0.2], "83o": [0.0, -0.2], "93s": [0.0, -0.2], "93o": [0.0, -0.2], "T3s": [0.0, -0.2], "T3o": [0.0, -0.2], "J3s": [0.0, -0.2], "J3o": [0.0, -0.2], "Q3s": [0.0, -0.2], "Q3o": [0.0, -0.2], "K3s": [0.0, -0.2], "K3o": [0.0, -0.2], "44": [0.0, -0.2], "54s": [0.0, -0.2], "54o": [0.0, -0.2], "64s": [0.0, -0.2], "64o": [0.0, -0.2], "74s": [0.0, -0.2], "74o": [0.0, -0.2], "84s": [0.0, -0.2], "84o": [0.0, -0.2], "94s": [0.0, -0.2], "94o": [0.0, -0.2], "T4s": [0.0, -0.2], "T4o": [0.0, -0.2], "J4s": [0.0, -0.2], "J4o": [0.0, -0.2], "Q4s": [0.0, -0.2], "Q4o": [0.0, -0.2], "K4s": [0.0, -0.2], "K4o": [0.0, -0.2], "55": [0.058, -0.2], "65s": [0.0, -0.2], "65o": [0.0, -0.2], "75s": [0.0, -0.2], "75o": [0.0, -0.2], "85s": [0.0, -0.2], "85o": [0.0, -0.2], "95s": [0.0, -0.2], "95o": [0.0, -0.2], "T5s": [0.0, -0.2], "T5o": [0.0, -0.2], "J5s": [0.0, -0.2], "J5o": [0.0, -0.2], "Q5s": [0.0, -0.2], "Q5o": [0.0, -0.2], "K5s": [0.0, -0.2], "K5o": [0.0, -0.2], "66": [0.192, -0.2], "76s": [0.0, -0.2], "76o": [0.0, -0.2], "86s": [0.0, -0.2], "86o": [0.0, -0.2], "96s": [0.0, -0.2], "96o": [0.0, -0.2], "T6s": [0.0, -0.2], "T6o": [0.0, -0.2], "J6s": [0.0, -0.2], "J6o": [0.0, -0.2], "Q6s": [0.0, -0.2], "Q6o": [0.0, -0.2], "K6s": [0.0, -0.2], "K6o": [0.0, -0.2], "77": [0.266, -0.2], "87s": [0.0, -0.2], "87o": [0.0, -0.2], "97s": [0.0, -0.2], "97o": [0.0, -0.2], "T7s": [0.0, -0.2], "T7o": [0.0, -0.2], "J7s": [0.0, -0.2], "J7o": [0.0, -0.2], "Q7s": [0.0, -0.2], "Q7o": [0.0, -0.2], "K7s": [0.0, -0.2], "K7o": [0.0, -0.2], "88": [0.109, -0.2], "98s": [0.0, -0.2], "98o": [0.0, -0.2], "T8s": [0.0, -0.2], "T8o": [0.0, -0.2], "J8s": [0.0, -0.2], "J8o": [0.0, -0.2], "Q8s": [0.0, -0.2], "Q8o": [0.0, -0.2], "K8s": [0.0, -0.2], "K8o": [0.0, -0.2], "99": [0.259, -0.2], "T9s": [0.265, -0.2], "T9o": [0.0, -0.2], "J9s": [0.0, -0.2], "J9o": [0.0, -0.2], "Q9s": [0.0, -0.2], "Q9o": [0.0, -0.2], "K9s": [0.91, -0.2], "K9o": [0.0, -0.2], "TT": [0.64, -0.2], "JTs": [0.353, -0.2], "JTo": [0.0, -0.2], "QTs": [0.439, -0.2], "QTo": [0.0, -0.2], "KTs": [0.665, -0.2], "KTo": [0.0, -0.2], "JJ": [1.0, -0.2], "QJs": [0.099, -0.2], "QJo": [0.0, -0.2], "KJs": [0.299, -0.2], "KJo": [0.0, -0.2], "QQ": [0.676, -0.2], "KQs": [0.0, -0.2], "KQo": [0.354, -0.2], "KK": [0.0, -0.2]},"Call":{"AA": [0.0, 0.92], "A2s": [0.0, -0.35], "A2o": [0.0, -0.37], "A3s": [0.0, -0.31], "A3o": [0.0, -0.39], "A4s": [0.0, -0.25], "A4o": [0.0, -0.36], "A5s": [0.0, -0.36], "A5o": [0.0, -0.35], "A6s": [0.0, -0.2], "A6o": [0.0, -0.36], "A7s": [0.0, -0.36], "A7o": [0.0, -0.44], "A8s": [0.0, -0.34], "A8o": [0.0, -0.45], "A9s": [0.0, -0.41], "A9o": [0.0, -0.45], "ATs": [0.0, -0.23], "ATo": [0.0, -0.41], "AJs": [0.0, -0.36], "AJo": [0.0, -0.52], "AQs": [0.0, -0.32], "AQo": [0.0, -0.39], "AKs": [0.03, -0.23], "AKo": [0.0, -0.32], "22": [0.0, -0.38], "32s": [0.0, -0.37], "32o": [0.0, -0.43], "42s": [0.0, -0.29], "42o": [0.0, -0.44], "52s": [0.0, -0.32], "52o": [0.0, -0.39], "62s": [0.0, -0.3], "62o": [0.0, -0.49], "72s": [0.0, -0.44], "72o": [0.0, -0.45], "82s": [0.0, -0.45], "82o": [0.0, -0.47], "92s": [0.0, -0.4], "92o": [0.0, -0.47], "T2s": [0.0, -0.37], "T2o": [0.0, -0.48], "J2s": [0.0, -0.42], "J2o": [0.0, -0.51], "Q2s": [0.0, -0.43], "Q2o": [0.0, -0.43], "K2s": [0.0, -0.42], "K2o": [0.0, -0.47], "33": [0.0, -0.37], "43s": [0.0, -0.36], "43o": [0.0, -0.39], "53s": [0.0, -0.22], "53o": [0.0, -0.37], "63s": [0.0, -0.32], "63o": [0.0, -0.41], "73s": [0.0, -0.31], "73o": [0.0, -0.46], "83s": [0.0, -0.43], "83o": [0.0, -0.43], "93s": [0.0, -0.42], "93o": [0.0, -0.44], "T3s": [0.0, -0.41], "T3o": [0.0, -0.49], "J3s": [0.0, -0.4], "J3o": [0.0, -0.48], "Q3s": [0.0, -0.42], "Q3o": [0.0, -0.49], "K3s": [0.0, -0.45], "K3o": [0.0, -0.47], "44": [0.0, -0.37], "54s": [0.0, -0.38], "54o": [0.0, -0.39], "64s": [0.0, -0.3], "64o": [0.0, -0.35], "74s": [0.0, -0.32], "74o": [0.0, -0.36], "84s": [0.0, -0.38], "84o": [0.0, -0.4], "94s": [0.0, -0.36], "94o": [0.0, -0.44], "T4s": [0.0, -0.4], "T4o": [0.0, -0.48], "J4s": [0.0, -0.51], "J4o": [0.0, -0.49], "Q4s": [0.0, -0.39], "Q4o": [0.0, -0.49], "K4s": [0.0, -0.41], "K4o": [0.0, -0.5], "55": [0.0, -0.43], "65s": [0.0, -0.23], "65o": [0.0, -0.33], "75s": [0.0, -0.28], "75o": [0.0, -0.38], "85s": [0.0, -0.29], "85o": [0.0, -0.39], "95s": [0.0, -0.41], "95o": [0.0, -0.47], "T5s": [0.0, -0.38], "T5o": [0.0, -0.44], "J5s": [0.0, -0.36], "J5o": [0.0, -0.53], "Q5s": [0.0, -0.43], "Q5o": [0.0, -0.49], "K5s": [0.0, -0.38], "K5o": [0.0, -0.49], "66": [0.0, -0.46], "76s": [0.0, -0.36], "76o": [0.0, -0.29], "86s": [0.0, -0.28], "86o": [0.0, -0.39], "96s": [0.0, -0.35], "96o": [0.0, -0.45], "T6s": [0.0, -0.36], "T6o": [0.0, -0.48], "J6s": [0.0, -0.43], "J6o": [0.0, -0.53], "Q6s": [0.0, -0.44], "Q6o": [0.0, -0.47], "K6s": [0.0, -0.31], "K6o": [0.0, -0.48], "77": [0.0, -0.45], "87s": [0.0, -0.41], "87o": [0.0, -0.39], "97s": [0.0, -0.34], "97o": [0.0, -0.42], "T7s": [0.0, -0.4], "T7o": [0.0, -0.46], "J7s": [0.0, -0.42], "J7o": [0.0, -0.48], "Q7s": [0.0, -0.46], "Q7o": [0.0, -0.46], "K7s": [0.0, -0.42], "K7o": [0.0, -0.5], "88": [0.0, -0.49], "98s": [0.0, -0.31], "98o": [0.0, -0.41], "T8s": [0.0, -0.27], "T8o": [0.0, -0.38], "J8s": [0.0, -0.37], "J8o": [0.0, -0.45], "Q8s": [0.0, -0.4], "Q8o": [0.0, -0.42], "K8s": [0.0, -0.37], "K8o": [0.0, -0.5], "99": [0.0, -0.43], "T9s": [0.0, -0.35], "T9o": [0.0, -0.41], "J9s": [0.0, -0.47], "J9o": [0.0, -0.48], "Q9s": [0.0, -0.44], "Q9o": [0.0, -0.46], "K9s": [0.0, -0.41], "K9o": [0.0, -0.54], "TT": [0.0, -0.42], "JTs": [0.0, -0.43], "JTo": [0.0, -0.48], "QTs": [0.0, -0.34], "QTo": [0.0, -0.49], "KTs": [0.0, -0.32], "KTo": [0.0, -0.57], "JJ": [0.0, -0.45], "QJs": [0.0, -0.42], "QJo": [0.0, -0.52], "KJs": [0.0, -0.42], "KJo": [0.0, -0.49], "QQ": [0.324, -0.3], "KQs": [0.0, -0.31], "KQo": [0.0, -0.5], "KK": [0.825, -0.02]},"ALLIN":{"AA": [1.0, 0.96], "A2s": [0.0, -0.46], "A2o": [0.0, -0.49], "A3s": [0.0, -0.38], "A3o": [0.0, -0.5], "A4s": [0.0, -0.37], "A4o": [0.0, -0.44], "A5s": [0.0, -0.42], "A5o": [0.0, -0.43], "A6s": [0.0, -0.29], "A6o": [0.0, -0.42], "A7s": [0.0, -0.4], "A7o": [0.0, -0.54], "A8s": [0.0, -0.39], "A8o": [0.0, -0.53], "A9s": [0.0, -0.47], "A9o": [0.0, -0.53], "ATs": [0.0, -0.26], "ATo": [0.0, -0.49], "AJs": [0.0, -0.34], "AJo": [0.0, -0.56], "AQs": [0.0, -0.35], "AQo": [0.0, -0.46], "AKs": [0.073, -0.22], "AKo": [0.0, -0.34], "22": [0.0, -0.53], "32s": [0.0, -0.51], "32o": [0.0, -0.62], "42s": [0.0, -0.39], "42o": [0.0, -0.61], "52s": [0.0, -0.42], "52o": [0.0, -0.54], "62s": [0.0, -0.38], "62o": [0.0, -0.65], "72s": [0.0, -0.59], "72o": [0.0, -0.67], "82s": [0.0, -0.62], "82o": [0.0, -0.65], "92s": [0.0, -0.56], "92o": [0.0, -0.63], "T2s": [0.0, -0.53], "T2o": [0.0, -0.65], "J2s": [0.0, -0.57], "J2o": [0.0, -0.73], "Q2s": [0.0, -0.6], "Q2o": [0.0, -0.63], "K2s": [0.0, -0.54], "K2o": [0.0, -0.68], "33": [0.0, -0.48], "43s": [0.0, -0.46], "43o": [0.0, -0.52], "53s": [0.0, -0.32], "53o": [0.0, -0.49], "63s": [0.0, -0.38], "63o": [0.0, -0.56], "73s": [0.0, -0.46], "73o": [0.0, -0.62], "83s": [0.0, -0.57], "83o": [0.0, -0.64], "93s": [0.0, -0.55], "93o": [0.0, -0.59], "T3s": [0.0, -0.51], "T3o": [0.0, -0.68], "J3s": [0.0, -0.56], "J3o": [0.0, -0.65], "Q3s": [0.0, -0.6], "Q3o": [0.0, -0.68], "K3s": [0.0, -0.61], "K3o": [0.0, -0.69], "44": [0.0, -0.49], "54s": [0.0, -0.44], "54o": [0.0, -0.52], "64s": [0.0, -0.43], "64o": [0.0, -0.47], "74s": [0.0, -0.51], "74o": [0.0, -0.49], "84s": [0.0, -0.51], "84o": [0.0, -0.55], "94s": [0.0, -0.53], "94o": [0.0, -0.61], "T4s": [0.0, -0.53], "T4o": [0.0, -0.65], "J4s": [0.0, -0.64], "J4o": [0.0, -0.67], "Q4s": [0.0, -0.5], "Q4o": [0.0, -0.66], "K4s": [0.0, -0.54], "K4o": [0.0, -0.68], "55": [0.0, -0.46], "65s": [0.0, -0.26], "65o": [0.0, -0.45], "75s": [0.0, -0.37], "75o": [0.0, -0.5], "85s": [0.0, -0.43], "85o": [0.0, -0.51], "95s": [0.0, -0.51], "95o": [0.0, -0.63], "T5s": [0.0, -0.5], "T5o": [0.0, -0.61], "J5s": [0.0, -0.51], "J5o": [0.0, -0.69], "Q5s": [0.0, -0.53], "Q5o": [0.0, -0.67], "K5s": [0.0, -0.47], "K5o": [0.0, -0.63], "66": [0.0, -0.48], "76s": [0.0, -0.47], "76o": [0.0, -0.36], "86s": [0.0, -0.37], "86o": [0.0, -0.48], "96s": [0.0, -0.45], "96o": [0.0, -0.59], "T6s": [0.0, -0.5], "T6o": [0.0, -0.62], "J6s": [0.0, -0.57], "J6o": [0.0, -0.7], "Q6s": [0.0, -0.59], "Q6o": [0.0, -0.65], "K6s": [0.0, -0.47], "K6o": [0.0, -0.66], "77": [0.0, -0.47], "87s": [0.0, -0.5], "87o": [0.0, -0.5], "97s": [0.0, -0.44], "97o": [0.0, -0.52], "T7s": [0.0, -0.5], "T7o": [0.0, -0.56], "J7s": [0.0, -0.48], "J7o": [0.0, -0.64], "Q7s": [0.0, -0.59], "Q7o": [0.0, -0.66], "K7s": [0.0, -0.51], "K7o": [0.0, -0.63], "88": [0.0, -0.52], "98s": [0.0, -0.4], "98o": [0.0, -0.5], "T8s": [0.0, -0.38], "T8o": [0.0, -0.52], "J8s": [0.0, -0.51], "J8o": [0.0, -0.58], "Q8s": [0.0, -0.59], "Q8o": [0.0, -0.58], "K8s": [0.0, -0.51], "K8o": [0.0, -0.66], "99": [0.0, -0.43], "T9s": [0.0, -0.46], "T9o": [0.0, -0.55], "J9s": [0.0, -0.54], "J9o": [0.0, -0.64], "Q9s": [0.0, -0.53], "Q9o": [0.0, -0.62], "K9s": [0.0, -0.54], "K9o": [0.0, -0.69], "TT": [0.0, -0.43], "JTs": [0.0, -0.51], "JTo": [0.0, -0.62], "QTs": [0.0, -0.44], "QTo": [0.0, -0.64], "KTs": [0.0, -0.41], "KTo": [0.0, -0.69], "JJ": [0.0, -0.46], "QJs": [0.0, -0.52], "QJo": [0.0, -0.67], "KJs": [0.0, -0.56], "KJo": [0.0, -0.61], "QQ": [0.0, -0.31], "KQs": [0.0, -0.39], "KQo": [0.0, -0.61], "KK": [0.175, -0.03]}}