{"Position":"SB","bb":23.0,"Fold":{"AA": [0.0, -8.0], "A2s": [0.0, -8.0], "A2o": [0.0, -8.0], "A3s": [0.0, -8.0], "A3o": [0.0, -8.0], "A4s": [0.0, -8.0], "A4o": [0.0, -8.0], "A5s": [0.0, -8.0], "A5o": [0.0, -8.0], "A6s": [0.0, -8.0], "A6o": [0.0, -8.0], "A7s": [0.159, -8.0], "A7o": [0.0, -8.0], "A8s": [0.695, -8.0], "A8o": [0.0, -8.0], "A9s": [0.0, -8.0], "A9o": [0.118, -8.0], "ATs": [0.0, -8.0], "ATo": [0.602, -8.0], "AJs": [0.0, -8.0], "AJo": [0.224, -8.0], "AQs": [0.0, -8.0], "AQo": [0.034, -8.0], "AKs": [0.0, -8.0], "AKo": [0.0, -8.0], "22": [0.0, -8.0], "32s": [0.0, -8.0], "32o": [0.0, -8.0], "42s": [0.0, -8.0], "42o": [0.0, -8.0], "52s": [0.0, -8.0], "52o": [0.0, -8.0], "62s": [0.0, -8.0], "62o": [0.0, -8.0], "72s": [0.0, -8.0], "72o": [0.0, -8.0], "82s": [0.0, -8.0], "82o": [0.0, -8.0], "92s": [0.0, -8.0], "92o": [0.0, -8.0], "T2s": [0.0, -8.0], "T2o": [0.0, -8.0], "J2s": [0.0, -8.0], "J2o": [0.0, -8.0], "Q2s": [0.0, -8.0], "Q2o": [0.0, -8.0], "K2s": [0.0, -8.0], "K2o": [0.0, -8.0], "33": [0.0, -8.0], "43s": [0.0, -8.0], "43o": [0.0, -8.0], "53s": [0.0, -8.0], "53o": [0.0, -8.0], "63s": [0.0, -8.0], "63o": [0.0, -8.0], "73s": [0.0, -8.0], "73o": [0.0, -8.0], "83s": [0.0, -8.0], "83o": [0.0, -8.0], "93s": [0.0, -8.0], "93o": [0.0, -8.0], "T3s": [0.0, -8.0], "T3o": [0.0, -8.0], "J3s": [0.0, -8.0], "J3o": [0.0, -8.0], "Q3s": [0.0, -8.0], "Q3o": [0.0, -8.0], "K3s": [0.0, -8.0], "K3o": [0.0, -8.0], "44": [0.0, -8.0], "54s": [0.0, -8.0], "54o": [0.0, -8.0], "64s": [0.0, -8.0], "64o": [0.0, -8.0], "74s": [0.0, -8.0], "74o": [0.0, -8.0], "84s": [0.0, -8.0], "84o": [0.0, -8.0], "94s": [0.0, -8.0], "94o": [0.0, -8.0], "T4s": [0.0, -8.0], "T4o": [0.0, -8.0], "J4s": [0.0, -8.0], "J4o": [0.0, -8.0], "Q4s": [0.0, -8.0], "Q4o": [0.0, -8.0], "K4s": [0.0, -8.0], "K4o": [0.0, -8.0], "55": [0.552, -8.0], "65s": [0.0, -8.0], "65o": [0.0, -8.0], "75s": [0.0, -8.0], "75o": [0.0, -8.0], "85s": [0.0, -8.0], "85o": [0.0, -8.0], "95s": [0.0, -8.0], "95o": [0.0, -8.0], "T5s": [0.0, -8.0], "T5o": [0.0, -8.0], "J5s": [0.0, -8.0], "J5o": [0.0, -8.0], "Q5s": [0.0, -8.0], "Q5o": [0.0, -8.0], "K5s": [0.0, -8.0], "K5o": [0.0, -8.0], "66": [0.0, -8.0], "76s": [0.0, -8.0], "76o": [0.0, -8.0], "86s": [0.0, -8.0], "86o": [0.0, -8.0], "96s": [0.0, -8.0], "96o": [0.0, -8.0], "T6s": [0.0, -8.0], "T6o": [0.0, -8.0], "J6s": [0.0, -8.0], "J6o": [0.0, -8.0], "Q6s": [0.0, -8.0], "Q6o": [0.0, -8.0], "K6s": [0.0, -8.0], "K6o": [0.0, -8.0], "77": [0.0, -8.0], "87s": [0.0, -8.0], "87o": [0.0, -8.0], "97s": [0.0, -8.0], "97o": [0.0, -8.0], "T7s": [0.0, -8.0], "T7o": [0.0, -8.0], "J7s": [0.0, -8.0], "J7o": [0.0, -8.0], "Q7s": [0.0, -8.0], "Q7o": [0.0, -8.0], "K7s": [0.0, -8.0], "K7o": [0.0, -8.0], "88": [0.0, -8.0], "98s": [0.0, -8.0], "98o": [0.0, -8.0], "T8s": [0.0, -8.0], "T8o": [0.0, -8.0], "J8s": [0.0, -8.0], "J8o": [0.0, -8.0], "Q8s": [0.0, -8.0], "Q8o": [0.0, -8.0], "K8s": [0.0, -8.0], "K8o": [0.0, -8.0], "99": [0.0, -8.0], "T9s": [0.193, -8.0], "T9o": [0.0, -8.0], "J9s": [0.0, -8.0], "J9o": [0.0, -8.0], "Q9s": [0.324, -8.0], "Q9o": [0.0, -8.0], "K9s": [0.438, -8.0], "K9o": [0.0, -8.0], "TT": [0.0, -8.0], "JTs": [0.109, -8.0], "JTo": [0.0, -8.0], "QTs": [0.232, -8.0], "QTo": [0.0, -8.0], "KTs": [0.089, -8.0], "KTo": [0.0, -8.0], "JJ": [0.457, -8.0], "QJs": [0.865, -8.0], "QJo": [0.0, -8.0], "KJs": [0.0, -8.0], "KJo": [0.0, -8.0], "QQ": [0.0, -8.0], "KQs": [0.0, -8.0], "KQo": [0.0, -8.0], "KK": [0.0, -8.0]},"Call":{"AA": [1.0, 25.66], "A2s": [0.0, -8.85], "A2o": [0.0, -11.67], "A3s": [0.0, -8.35], "A3o": [0.0, -11.38], "A4s": [0.0, -8.04], "A4o": [0.0, -11.02], "A5s": [0.0, -7.78], "A5o": [0.0, -10.68], "A6s": [0.0, -8.94], "A6o": [0.0, -12.19], "A7s": [0.0, -9.25], "A7o": [0.0, -12.07], "A8s": [0.0, -8.93], "A8o": [0.0, -12.11], "A9s": [0.0, -9.27], "A9o": [0.0, -12.3], "ATs": [0.0, -8.72], "ATo": [0.0, -11.79], "AJs": [0.0, -8.61], "AJo": [0.0, -11.58], "AQs": [0.0, -7.43], "AQo": [0.0, -10.44], "AKs": [0.362, -2.86], "AKo": [0.0, -5.7], "22": [0.0, -11.2], "32s": [0.0, -10.93], "32o": [0.0, -13.85], "42s": [0.0, -10.7], "42o": [0.0, -13.58], "52s": [0.0, -10.36], "52o": [0.0, -13.27], "62s": [0.0, -11.29], "62o": [0.0, -14.14], "72s": [0.0, -12.39], "72o": [0.0, -15.39], "82s": [0.0, -12.13], "82o": [0.0, -15.06], "92s": [0.0, -12.42], "92o": [0.0, -15.3], "T2s": [0.0, -12.36], "T2o": [0.0, -15.39], "J2s": [0.0, -12.8], "J2o": [0.0, -15.96], "Q2s": [0.0, -13.1], "Q2o": [0.0, -16.29], "K2s": [0.0, -10.66], "K2o": [0.0, -13.71], "33": [0.0, -11.05], "43s": [0.0, -9.49], "43o": [0.0, -12.4], "53s": [0.0, -9.27], "53o": [0.0, -12.03], "63s": [0.0, -10.06], "63o": [0.0, -12.96], "73s": [0.0, -11.23], "73o": [0.0, -14.1], "83s": [0.0, -12.11], "83o": [0.0, -15.12], "93s": [0.0, -12.13], "93o": [0.0, -14.95], "T3s": [0.0, -12.13], "T3o": [0.0, -15.0], "J3s": [0.0, -12.57], "J3o": [0.0, -15.7], "Q3s": [0.0, -12.84], "Q3o": [0.0, -15.93], "K3s": [0.0, -10.53], "K3o": [0.0, -13.49], "44": [0.0, -10.63], "54s": [0.0, -8.24], "54o": [0.0, -10.98], "64s": [0.0, -8.88], "64o": [0.0, -11.65], "74s": [0.0, -9.96], "74o": [0.0, -12.8], "84s": [0.0, -10.94], "84o": [0.0, -13.89], "94s": [0.0, -12.04], "94o": [0.0, -14.94], "T4s": [0.0, -11.82], "T4o": [0.0, -14.8], "J4s": [0.0, -12.5], "J4o": [0.0, -15.38], "Q4s": [0.0, -12.55], "Q4o": [0.0, -15.75], "K4s": [0.0, -10.03], "K4o": [0.0, -13.09], "55": [0.0, -10.41], "65s": [0.0, -7.87], "65o": [0.0, -10.54], "75s": [0.0, -9.18], "75o": [0.0, -11.76], "85s": [0.0, -10.13], "85o": [0.0, -12.76], "95s": [0.0, -11.03], "95o": [0.0, -13.85], "T5s": [0.0, -11.8], "T5o": [0.0, -14.7], "J5s": [0.0, -12.18], "J5o": [0.0, -15.14], "Q5s": [0.0, -12.37], "Q5o": [0.0, -15.51], "K5s": [0.0, -9.79], "K5o": [0.0, -12.78], "66": [0.0, -10.46], "76s": [0.0, -8.27], "76o": [0.0, -10.72], "86s": [0.0, -9.15], "86o": [0.0, -11.85], "96s": [0.0, -10.24], "96o": [0.0, -13.04], "T6s": [0.0, -10.91], "T6o": [0.0, -13.96], "J6s": [0.0, -12.43], "J6o": [0.0, -15.46], "Q6s": [0.0, -12.35], "Q6o": [0.0, -15.58], "K6s": [0.0, -10.13], "K6o": [0.0, -13.03], "77": [0.0, -10.53], "87s": [0.0, -8.47], "87o": [0.0, -11.19], "97s": [0.0, -9.45], "97o": [0.0, -12.19], "T7s": [0.0, -10.31], "T7o": [0.0, -13.21], "J7s": [0.0, -11.59], "J7o": [0.0, -14.59], "Q7s": [0.0, -12.74], "Q7o": [0.0, -15.71], "K7s": [0.0, -9.79], "K7o": [0.0, -13.04], "88": [0.0, -10.26], "98s": [0.0, -9.07], "98o": [0.0, -11.93], "T8s": [0.0, -9.74], "T8o": [0.0, -12.54], "J8s": [0.0, -10.96], "J8o": [0.0, -13.94], "Q8s": [0.0, -12.05], "Q8o": [0.0, -14.99], "K8s": [0.0, -10.15], "K8o": [0.0, -13.17], "99": [0.0, -10.49], "T9s": [0.0, -9.46], "T9o": [0.0, -12.32], "J9s": [0.0, -11.01], "J9o": [0.0, -13.75], "Q9s": [0.0, -11.7], "Q9o": [0.0, -14.58], "K9s": [0.0, -10.07], "K9o": [0.0, -12.74], "TT": [0.0, -10.45], "JTs": [0.0, -10.38], "JTo": [0.0, -13.41], "QTs": [0.0, -11.24], "QTo": [0.0, -14.07], "KTs": [0.0, -9.35], "KTo": [0.0, -12.23], "JJ": [0.0, -10.73], "QJs": [0.0, -11.26], "QJo": [0.0, -14.66], "KJs": [0.0, -9.79], "KJo": [0.0, -12.86], "QQ": [0.0, -7.74], "KQs": [0.0, -9.84], "KQo": [0.0, -12.98], "KK": [0.384, 5.8]}}