{"Position":"BB","bb":23.0,"Fold":{"AA": [0.0, -1.0], "A2s": [0.0, -1.0], "A2o": [0.0, -1.0], "A3s": [0.0, -1.0], "A3o": [0.0, -1.0], "A4s": [0.0, -1.0], "A4o": [0.0, -1.0], "A5s": [0.0, -1.0], "A5o": [0.0, -1.0], "A6s": [0.0, -1.0], "A6o": [0.0, -1.0], "A7s": [0.0, -1.0], "A7o": [0.0, -1.0], "A8s": [0.0, -1.0], "A8o": [0.0, -1.0], "A9s": [0.0, -1.0], "A9o": [0.0, -1.0], "ATs": [0.0, -1.0], "ATo": [0.0, -1.0], "AJs": [0.0, -1.0], "AJo": [0.0, -1.0], "AQs": [0.0, -1.0], "AQo": [0.0, -1.0], "AKs": [0.0, -1.0], "AKo": [0.0, -1.0], "22": [0.0, -1.0], "32s": [0.0, -1.0], "32o": [1.0, -1.0], "42s": [0.0, -1.0], "42o": [0.088, -1.0], "52s": [0.0, -1.0], "52o": [0.0, -1.0], "62s": [0.0, -1.0], "62o": [1.0, -1.0], "72s": [0.0, -1.0], "72o": [1.0, -1.0], "82s": [0.0, -1.0], "82o": [1.0, -1.0], "92s": [0.0, -1.0], "92o": [1.0, -1.0], "T2s": [0.0, -1.0], "T2o": [1.0, -1.0], "J2s": [0.0, -1.0], "J2o": [0.0, -1.0], "Q2s": [0.0, -1.0], "Q2o": [0.0, -1.0], "K2s": [0.0, -1.0], "K2o": [0.0, -1.0], "33": [0.0, -1.0], "43s": [0.0, -1.0], "43o": [0.0, -1.0], "53s": [0.0, -1.0], "53o": [0.0, -1.0], "63s": [0.0, -1.0], "63o": [0.0, -1.0], "73s": [0.0, -1.0], "73o": [1.0, -1.0], "83s": [0.0, -1.0], "83o": [1.0, -1.0], "93s": [0.0, -1.0], "93o": [1.0, -1.0], "T3s": [0.0, -1.0], "T3o": [1.0, -1.0], "J3s": [0.0, -1.0], "J3o": [0.0, -1.0], "Q3s": [0.0, -1.0], "Q3o": [0.0, -1.0], "K3s": [0.0, -1.0], "K3o": [0.0, -1.0], "44": [0.0, -1.0], "54s": [0.0, -1.0], "54o": [0.0, -1.0], "64s": [0.0, -1.0], "64o": [0.0, -1.0], "74s": [0.0, -1.0], "74o": [0.0, -1.0], "84s": [0.0, -1.0], "84o": [1.0, -1.0], "94s": [0.0, -1.0], "94o": [1.0, -1.0], "T4s": [0.0, -1.0], "T4o": [0.0, -1.0], "J4s": [0.0, -1.0], "J4o": [0.0, -1.0], "Q4s": [0.0, -1.0], "Q4o": [0.0, -1.0], "K4s": [0.0, -1.0], "K4o": [0.0, -1.0], "55": [0.0, -1.0], "65s": [0.0, -1.0], "65o": [0.0, -1.0], "75s": [0.0, -1.0], "75o": [0.0, -1.0], "85s": [0.0, -1.0], "85o": [0.0, -1.0], "95s": [0.0, -1.0], "95o": [0.0, -1.0], "T5s": [0.0, -1.0], "T5o": [0.0, -1.0], "J5s": [0.0, -1.0], "J5o": [0.0, -1.0], "Q5s": [0.0, -1.0], "Q5o": [0.0, -1.0], "K5s": [0.0, -1.0], "K5o": [0.0, -1.0], "66": [0.0, -1.0], "76s": [0.0, -1.0], "76o": [0.0, -1.0], "86s": [0.0, -1.0], "86o": [0.0, -1.0], "96s": [0.0, -1.0], "96o": [0.0, -1.0], "T6s": [0.0, -1.0], "T6o": [0.0, -1.0], "J6s": [0.0, -1.0], "J6o": [0.0, -1.0], "Q6s": [0.0, -1.0], "Q6o": [0.0, -1.0], "K6s": [0.0, -1.0], "K6o": [0.0, -1.0], "77": [0.0, -1.0], "87s": [0.0, -1.0], "87o": [0.0, -1.0], "97s": [0.0, -1.0], "97o": [0.0, -1.0], "T7s": [0.0, -1.0], "T7o": [0.0, -1.0], "J7s": [0.0, -1.0], "J7o": [0.0, -1.0], "Q7s": [0.0, -1.0], "Q7o": [0.0, -1.0], "K7s": [0.0, -1.0], "K7o": [0.0, -1.0], "88": [0.0, -1.0], "98s": [0.0, -1.0], "98o": [0.0, -1.0], "T8s": [0.0, -1.0], "T8o": [0.0, -1.0], "J8s": [0.0, -1.0], "J8o": [0.0, -1.0], "Q8s": [0.0, -1.0], "Q8o": [0.0, -1.0], "K8s": [0.0, -1.0], "K8o": [0.0, -1.0], "99": [0.0, -1.0], "T9s": [0.0, -1.0], "T9o": [0.0, -1.0], "J9s": [0.0, -1.0], "J9o": [0.0, -1.0], "Q9s": [0.0, -1.0], "Q9o": [0.0, -1.0], "K9s": [0.0, -1.0], "K9o": [0.0, -1.0], "TT": [0.0, -1.0], "JTs": [0.0, -1.0], "JTo": [0.0, -1.0], "QTs": [0.0, -1.0], "QTo": [0.0, -1.0], "KTs": [0.0, -1.0], "KTo": [0.0, -1.0], "JJ": [0.0, -1.0], "QJs": [0.0, -1.0], "QJo": [0.0, -1.0], "KJs": [0.0, -1.0], "KJo": [0.0, -1.0], "QQ": [0.0, -1.0], "KQs": [0.0, -1.0], "KQo": [0.0, -1.0], "KK": [0.0, -1.0]},"Call":{"AA": [0.0, 7.64], "A2s": [0.13, 0.5], "A2o": [0.0, -0.09], "A3s": [1.0, 0.55], "A3o": [0.276, -0.04], "A4s": [0.99, 0.61], "A4o": [0.0, 0.02], "A5s": [1.0, 0.71], "A5o": [0.0, 0.12], "A6s": [1.0, 0.7], "A6o": [0.954, 0.11], "A7s": [1.0, 0.83], "A7o": [0.77, 0.23], "A8s": [1.0, 1.08], "A8o": [0.251, 0.48], "A9s": [0.0, 1.37], "A9o": [0.0, 0.79], "ATs": [0.0, 2.01], "ATo": [0.0, 1.46], "AJs": [0.0, 2.38], "AJo": [0.0, 1.85], "AQs": [0.0, 2.81], "AQo": [0.0, 2.31], "AKs": [0.0, 3.37], "AKo": [0.0, 2.9], "22": [0.0, -0.12], "32s": [1.0, -0.59], "32o": [0.0, -1.03], "42s": [1.0, -0.55], "42o": [0.912, -1.0], "52s": [1.0, -0.53], "52o": [1.0, -0.98], "62s": [1.0, -0.62], "62o": [0.0, -1.06], "72s": [1.0, -0.71], "72o": [0.0, -1.13], "82s": [1.0, -0.68], "82o": [0.0, -1.12], "92s": [1.0, -0.65], "92o": [0.0, -1.09], "T2s": [1.0, -0.55], "T2o": [0.0, -1.0], "J2s": [1.0, -0.52], "J2o": [0.966, -0.98], "Q2s": [1.0, -0.37], "Q2o": [0.878, -0.87], "K2s": [1.0, -0.21], "K2o": [1.0, -0.74], "33": [0.0, -0.06], "43s": [1.0, -0.46], "43o": [1.0, -0.91], "53s": [1.0, -0.41], "53o": [1.0, -0.86], "63s": [1.0, -0.52], "63o": [1.0, -0.96], "73s": [1.0, -0.61], "73o": [0.0, -1.05], "83s": [1.0, -0.7], "83o": [0.0, -1.13], "93s": [1.0, -0.65], "93o": [0.0, -1.09], "T3s": [1.0, -0.55], "T3o": [0.0, -1.01], "J3s": [1.0, -0.52], "J3o": [0.947, -0.99], "Q3s": [1.0, -0.38], "Q3o": [0.901, -0.87], "K3s": [1.0, -0.2], "K3o": [0.923, -0.74], "44": [0.0, 0.06], "54s": [1.0, -0.29], "54o": [1.0, -0.76], "64s": [1.0, -0.38], "64o": [1.0, -0.84], "74s": [1.0, -0.49], "74o": [1.0, -0.94], "84s": [1.0, -0.58], "84o": [0.0, -1.02], "94s": [1.0, -0.63], "94o": [0.0, -1.07], "T4s": [1.0, -0.53], "T4o": [0.926, -0.99], "J4s": [1.0, -0.49], "J4o": [0.938, -0.97], "Q4s": [1.0, -0.34], "Q4o": [0.834, -0.84], "K4s": [1.0, -0.16], "K4o": [0.993, -0.7], "55": [0.0, 0.19], "65s": [1.0, -0.26], "65o": [1.0, -0.73], "75s": [1.0, -0.36], "75o": [1.0, -0.82], "85s": [1.0, -0.45], "85o": [1.0, -0.91], "95s": [1.0, -0.52], "95o": [1.0, -0.98], "T5s": [1.0, -0.51], "T5o": [0.99, -0.97], "J5s": [1.0, -0.45], "J5o": [0.87, -0.93], "Q5s": [1.0, -0.29], "Q5o": [1.0, -0.79], "K5s": [1.0, -0.09], "K5o": [0.895, -0.63], "66": [0.0, 0.39], "76s": [1.0, -0.21], "76o": [1.0, -0.68], "86s": [1.0, -0.29], "86o": [1.0, -0.75], "96s": [1.0, -0.35], "96o": [1.0, -0.82], "T6s": [1.0, -0.37], "T6o": [0.9, -0.84], "J6s": [1.0, -0.41], "J6o": [1.0, -0.88], "Q6s": [1.0, -0.24], "Q6o": [1.0, -0.74], "K6s": [0.0, -0.04], "K6o": [0.925, -0.59], "77": [0.0, 0.62], "87s": [0.831, -0.19], "87o": [1.0, -0.66], "97s": [1.0, -0.24], "97o": [1.0, -0.7], "T7s": [1.0, -0.24], "T7o": [0.981, -0.72], "J7s": [1.0, -0.3], "J7o": [0.926, -0.78], "Q7s": [1.0, -0.24], "Q7o": [1.0, -0.74], "K7s": [0.0, 0.01], "K7o": [0.92, -0.56], "88": [0.0, 0.94], "98s": [0.4, -0.12], "98o": [1.0, -0.58], "T8s": [0.623, -0.06], "T8o": [1.0, -0.53], "J8s": [1.0, -0.08], "J8o": [0.935, -0.57], "Q8s": [1.0, -0.02], "Q8o": [0.958, -0.54], "K8s": [1.0, 0.13], "K8o": [1.0, -0.44], "99": [0.0, 1.5], "T9s": [0.0, 0.2], "T9o": [1.0, -0.27], "J9s": [0.634, 0.19], "J9o": [1.0, -0.31], "Q9s": [1.0, 0.26], "Q9o": [1.0, -0.26], "K9s": [1.0, 0.45], "K9o": [1.0, -0.13], "TT": [0.0, 2.27], "JTs": [0.0, 0.6], "JTo": [0.95, 0.12], "QTs": [1.0, 0.72], "QTo": [1.0, 0.2], "KTs": [1.0, 0.97], "KTo": [1.0, 0.4], "JJ": [0.0, 3.03], "QJs": [0.0, 0.89], "QJo": [0.828, 0.36], "KJs": [1.0, 1.19], "KJo": [1.0, 0.64], "QQ": [0.0, 4.01], "KQs": [1.0, 1.52], "KQo": [0.109, 0.99], "KK": [0.0, 5.3]},"ALLIN":{"AA": [0.0, 7.79], "A2s": [0.87, 0.5], "A2o": [0.836, -0.08], "A3s": [0.0, 0.53], "A3o": [0.717, -0.04], "A4s": [0.01, 0.61], "A4o": [1.0, 0.04], "A5s": [0.0, 0.7], "A5o": [1.0, 0.13], "A6s": [0.0, 0.61], "A6o": [0.0, 0.05], "A7s": [0.0, 0.75], "A7o": [0.0, 0.21], "A8s": [0.0, 1.01], "A8o": [0.677, 0.48], "A9s": [0.866, 1.5], "A9o": [1.0, 1.01], "ATs": [0.321, 2.4], "ATo": [1.0, 1.97], "AJs": [0.309, 3.06], "AJo": [1.0, 2.68], "AQs": [0.926, 3.83], "AQo": [1.0, 3.51], "AKs": [0.0, 4.58], "AKo": [0.913, 4.31], "22": [1.0, 0.44], "32s": [0.0, -1.3], "32o": [0.0, -1.98], "42s": [0.0, -1.19], "42o": [0.0, -1.86], "52s": [0.0, -1.09], "52o": [0.0, -1.76], "62s": [0.0, -1.25], "62o": [0.0, -1.94], "72s": [0.0, -1.33], "72o": [0.0, -2.02], "82s": [0.0, -1.26], "82o": [0.0, -1.94], "92s": [0.0, -1.14], "92o": [0.0, -1.81], "T2s": [0.0, -0.92], "T2o": [0.0, -1.59], "J2s": [0.0, -0.78], "J2o": [0.0, -1.44], "Q2s": [0.0, -0.57], "Q2o": [0.0, -1.22], "K2s": [0.0, -0.3], "K2o": [0.0, -0.95], "33": [0.88, 0.5], "43s": [0.0, -1.0], "43o": [0.0, -1.67], "53s": [0.0, -0.9], "53o": [0.0, -1.56], "63s": [0.0, -1.07], "63o": [0.0, -1.74], "73s": [0.0, -1.15], "73o": [0.0, -1.83], "83s": [0.0, -1.28], "83o": [0.0, -1.96], "93s": [0.0, -1.11], "93o": [0.0, -1.78], "T3s": [0.0, -0.9], "T3o": [0.0, -1.56], "J3s": [0.0, -0.75], "J3o": [0.0, -1.41], "Q3s": [0.0, -0.54], "Q3o": [0.0, -1.19], "K3s": [0.0, -0.27], "K3o": [0.0, -0.92], "44": [1.0, 0.71], "54s": [0.0, -0.65], "54o": [0.0, -1.3], "64s": [0.0, -0.81], "64o": [0.0, -1.47], "74s": [0.0, -0.9], "74o": [0.0, -1.56], "84s": [0.0, -1.03], "84o": [0.0, -1.69], "94s": [0.0, -1.07], "94o": [0.0, -1.74], "T4s": [0.0, -0.82], "T4o": [0.0, -1.47], "J4s": [0.0, -0.67], "J4o": [0.0, -1.32], "Q4s": [0.0, -0.45], "Q4o": [0.0, -1.1], "K4s": [0.0, -0.19], "K4o": [0.0, -0.83], "55": [1.0, 1.05], "65s": [0.0, -0.55], "65o": [0.0, -1.19], "75s": [0.0, -0.63], "75o": [0.0, -1.28], "85s": [0.0, -0.76], "85o": [0.0, -1.41], "95s": [0.0, -0.81], "95o": [0.0, -1.46], "T5s": [0.0, -0.76], "T5o": [0.0, -1.41], "J5s": [0.0, -0.57], "J5o": [0.0, -1.22], "Q5s": [0.0, -0.35], "Q5o": [0.0, -1.0], "K5s": [0.0, -0.09], "K5o": [0.0, -0.73], "66": [1.0, 1.4], "76s": [0.0, -0.38], "76o": [0.0, -1.02], "86s": [0.0, -0.5], "86o": [0.0, -1.14], "96s": [0.0, -0.54], "96o": [0.0, -1.19], "T6s": [0.0, -0.51], "T6o": [0.0, -1.16], "J6s": [0.0, -0.55], "J6o": [0.0, -1.2], "Q6s": [0.0, -0.29], "Q6o": [0.0, -0.92], "K6s": [1.0, -0.03], "K6o": [0.0, -0.66], "77": [1.0, 1.78], "87s": [0.0, -0.26], "87o": [0.0, -0.88], "97s": [0.0, -0.29], "97o": [0.0, -0.92], "T7s": [0.0, -0.26], "T7o": [0.0, -0.89], "J7s": [0.0, -0.3], "J7o": [0.0, -0.93], "Q7s": [0.0, -0.26], "Q7o": [0.0, -0.9], "K7s": [1.0, 0.05], "K7o": [0.0, -0.58], "88": [1.0, 2.25], "98s": [0.0, -0.12], "98o": [0.0, -0.73], "T8s": [0.0, -0.06], "T8o": [0.0, -0.67], "J8s": [0.0, -0.1], "J8o": [0.0, -0.72], "Q8s": [0.0, -0.08], "Q8o": [0.0, -0.7], "K8s": [0.0, 0.01], "K8o": [0.0, -0.61], "99": [1.0, 2.84], "T9s": [0.535, 0.23], "T9o": [0.0, -0.36], "J9s": [0.277, 0.19], "J9o": [0.0, -0.4], "Q9s": [0.0, 0.22], "Q9o": [0.0, -0.38], "K9s": [0.0, 0.31], "K9o": [0.0, -0.3], "TT": [1.0, 3.71], "JTs": [0.786, 0.66], "JTo": [0.05, 0.12], "QTs": [0.0, 0.7], "QTo": [0.0, 0.16], "KTs": [0.0, 0.83], "KTo": [0.0, 0.29], "JJ": [1.0, 4.41], "QJs": [1.0, 0.9], "QJo": [0.172, 0.36], "KJs": [0.0, 1.07], "KJo": [0.0, 0.55], "QQ": [0.299, 5.21], "KQs": [0.0, 1.49], "KQo": [0.891, 0.99], "KK": [0.0, 6.1]},"Raise 75%":{"AA": [1.0, 8.62], "A2s": [0.0, 0.3], "A2o": [0.164, -0.08], "A3s": [0.0, 0.33], "A3o": [0.007, -0.04], "A4s": [0.0, 0.42], "A4o": [0.0, 0.03], "A5s": [0.0, 0.59], "A5o": [0.0, 0.13], "A6s": [0.0, 0.55], "A6o": [0.046, 0.11], "A7s": [0.0, 0.74], "A7o": [0.23, 0.23], "A8s": [0.0, 1.07], "A8o": [0.073, 0.48], "A9s": [0.134, 1.5], "A9o": [0.0, 0.91], "ATs": [0.679, 2.4], "ATo": [0.0, 1.87], "AJs": [0.691, 3.06], "AJo": [0.0, 2.57], "AQs": [0.074, 3.83], "AQo": [0.0, 3.39], "AKs": [1.0, 4.67], "AKo": [0.087, 4.3], "22": [0.0, 0.42], "32s": [0.0, -0.8], "32o": [0.0, -1.14], "42s": [0.0, -0.76], "42o": [0.0, -1.09], "52s": [0.0, -0.71], "52o": [0.0, -1.05], "62s": [0.0, -0.83], "62o": [0.0, -1.18], "72s": [0.0, -0.9], "72o": [0.0, -1.25], "82s": [0.0, -0.85], "82o": [0.0, -1.21], "92s": [0.0, -0.77], "92o": [0.0, -1.13], "T2s": [0.0, -0.65], "T2o": [0.0, -1.01], "J2s": [0.0, -0.61], "J2o": [0.034, -0.99], "Q2s": [0.0, -0.49], "Q2o": [0.122, -0.87], "K2s": [0.0, -0.35], "K2o": [0.0, -0.74], "33": [0.12, 0.49], "43s": [0.0, -0.67], "43o": [0.0, -1.01], "53s": [0.0, -0.61], "53o": [0.0, -0.95], "63s": [0.0, -0.74], "63o": [0.0, -1.08], "73s": [0.0, -0.81], "73o": [0.0, -1.15], "83s": [0.0, -0.86], "83o": [0.0, -1.22], "93s": [0.0, -0.77], "93o": [0.0, -1.13], "T3s": [0.0, -0.65], "T3o": [0.0, -1.02], "J3s": [0.0, -0.61], "J3o": [0.053, -0.99], "Q3s": [0.0, -0.49], "Q3o": [0.099, -0.87], "K3s": [0.0, -0.34], "K3o": [0.077, -0.74], "44": [0.0, 0.68], "54s": [0.0, -0.45], "54o": [0.0, -0.83], "64s": [0.0, -0.62], "64o": [0.0, -0.95], "74s": [0.0, -0.69], "74o": [0.0, -1.03], "84s": [0.0, -0.75], "84o": [0.0, -1.1], "94s": [0.0, -0.77], "94o": [0.0, -1.12], "T4s": [0.0, -0.63], "T4o": [0.074, -1.0], "J4s": [0.0, -0.59], "J4o": [0.062, -0.97], "Q4s": [0.0, -0.46], "Q4o": [0.166, -0.84], "K4s": [0.0, -0.31], "K4o": [0.007, -0.7], "55": [0.0, 0.97], "65s": [0.0, -0.38], "65o": [0.0, -0.82], "75s": [0.0, -0.52], "75o": [0.0, -0.89], "85s": [0.0, -0.62], "85o": [0.0, -0.96], "95s": [0.0, -0.64], "95o": [0.0, -0.99], "T5s": [0.0, -0.61], "T5o": [0.01, -0.97], "J5s": [0.0, -0.55], "J5o": [0.13, -0.93], "Q5s": [0.0, -0.41], "Q5o": [0.0, -0.79], "K5s": [0.0, -0.25], "K5o": [0.105, -0.63], "66": [0.0, 1.27], "76s": [0.0, -0.24], "76o": [0.0, -0.76], "86s": [0.0, -0.38], "86o": [0.0, -0.82], "96s": [0.0, -0.48], "96o": [0.0, -0.84], "T6s": [0.0, -0.48], "T6o": [0.1, -0.84], "J6s": [0.0, -0.53], "J6o": [0.0, -0.9], "Q6s": [0.0, -0.36], "Q6o": [0.0, -0.75], "K6s": [0.0, -0.17], "K6o": [0.075, -0.59], "77": [0.0, 1.61], "87s": [0.169, -0.19], "87o": [0.0, -0.73], "97s": [0.0, -0.28], "97o": [0.0, -0.74], "T7s": [0.0, -0.29], "T7o": [0.019, -0.72], "J7s": [0.0, -0.39], "J7o": [0.074, -0.78], "Q7s": [0.0, -0.38], "Q7o": [0.0, -0.75], "K7s": [0.0, -0.14], "K7o": [0.08, -0.56], "88": [0.0, 2.08], "98s": [0.6, -0.12], "98o": [0.0, -0.63], "T8s": [0.377, -0.06], "T8o": [0.0, -0.54], "J8s": [0.0, -0.12], "J8o": [0.065, -0.57], "Q8s": [0.0, -0.15], "Q8o": [0.042, -0.54], "K8s": [0.0, -0.08], "K8o": [0.0, -0.44], "99": [0.0, 2.69], "T9s": [0.465, 0.23], "T9o": [0.0, -0.34], "J9s": [0.089, 0.19], "J9o": [0.0, -0.34], "Q9s": [0.0, 0.17], "Q9o": [0.0, -0.3], "K9s": [0.0, 0.24], "K9o": [0.0, -0.18], "TT": [0.0, 3.64], "JTs": [0.214, 0.66], "JTo": [0.0, 0.05], "QTs": [0.0, 0.67], "QTo": [0.0, 0.05], "KTs": [0.0, 0.85], "KTo": [0.0, 0.24], "JJ": [0.0, 4.4], "QJs": [0.0, 0.84], "QJo": [0.0, 0.22], "KJs": [0.0, 1.13], "KJo": [0.0, 0.52], "QQ": [0.701, 5.21], "KQs": [0.0, 1.45], "KQo": [0.0, 0.86], "KK": [1.0, 6.24]}}