{"Position":"UTG1","bb":23.0,"Fold":{"AA": [0.0, -2.0], "A2s": [0.0, -2.0], "A2o": [0.0, -2.0], "A3s": [1.0, -2.0], "A3o": [0.0, -2.0], "A4s": [1.0, -2.0], "A4o": [0.0, -2.0], "A5s": [0.349, -2.0], "A5o": [0.0, -2.0], "A6s": [0.0, -2.0], "A6o": [0.0, -2.0], "A7s": [0.278, -2.0], "A7o": [0.0, -2.0], "A8s": [0.846, -2.0], "A8o": [0.0, -2.0], "A9s": [1.0, -2.0], "A9o": [1.0, -2.0], "ATs": [0.698, -2.0], "ATo": [0.568, -2.0], "AJs": [0.0, -2.0], "AJo": [1.0, -2.0], "AQs": [1.0, -2.0], "AQo": [1.0, -2.0], "AKs": [0.0, -2.0], "AKo": [0.0, -2.0], "22": [0.0, -2.0], "32s": [0.0, -2.0], "32o": [0.0, -2.0], "42s": [0.0, -2.0], "42o": [0.0, -2.0], "52s": [0.0, -2.0], "52o": [0.0, -2.0], "62s": [0.0, -2.0], "62o": [0.0, -2.0], "72s": [0.0, -2.0], "72o": [0.0, -2.0], "82s": [0.0, -2.0], "82o": [0.0, -2.0], "92s": [0.0, -2.0], "92o": [0.0, -2.0], "T2s": [0.0, -2.0], "T2o": [0.0, -2.0], "J2s": [0.0, -2.0], "J2o": [0.0, -2.0], "Q2s": [0.0, -2.0], "Q2o": [0.0, -2.0], "K2s": [0.0, -2.0], "K2o": [0.0, -2.0], "33": [0.0, -2.0], "43s": [0.0, -2.0], "43o": [0.0, -2.0], "53s": [0.0, -2.0], "53o": [0.0, -2.0], "63s": [0.0, -2.0], "63o": [0.0, -2.0], "73s": [0.0, -2.0], "73o": [0.0, -2.0], "83s": [0.0, -2.0], "83o": [0.0, -2.0], "93s": [0.0, -2.0], "93o": [0.0, -2.0], "T3s": [0.0, -2.0], "T3o": [0.0, -2.0], "J3s": [0.0, -2.0], "J3o": [0.0, -2.0], "Q3s": [0.0, -2.0], "Q3o": [0.0, -2.0], "K3s": [0.0, -2.0], "K3o": [0.0, -2.0], "44": [0.0, -2.0], "54s": [0.0, -2.0], "54o": [0.0, -2.0], "64s": [0.0, -2.0], "64o": [0.0, -2.0], "74s": [0.0, -2.0], "74o": [0.0, -2.0], "84s": [0.0, -2.0], "84o": [0.0, -2.0], "94s": [0.0, -2.0], "94o": [0.0, -2.0], "T4s": [0.0, -2.0], "T4o": [0.0, -2.0], "J4s": [0.0, -2.0], "J4o": [0.0, -2.0], "Q4s": [0.0, -2.0], "Q4o": [0.0, -2.0], "K4s": [0.0, -2.0], "K4o": [0.0, -2.0], "55": [0.224, -2.0], "65s": [0.0, -2.0], "65o": [0.0, -2.0], "75s": [0.0, -2.0], "75o": [0.0, -2.0], "85s": [0.0, -2.0], "85o": [0.0, -2.0], "95s": [0.0, -2.0], "95o": [0.0, -2.0], "T5s": [0.0, -2.0], "T5o": [0.0, -2.0], "J5s": [0.0, -2.0], "J5o": [0.0, -2.0], "Q5s": [0.0, -2.0], "Q5o": [0.0, -2.0], "K5s": [0.0, -2.0], "K5o": [0.0, -2.0], "66": [0.0, -2.0], "76s": [0.0, -2.0], "76o": [0.0, -2.0], "86s": [0.0, -2.0], "86o": [0.0, -2.0], "96s": [0.0, -2.0], "96o": [0.0, -2.0], "T6s": [0.0, -2.0], "T6o": [0.0, -2.0], "J6s": [0.0, -2.0], "J6o": [0.0, -2.0], "Q6s": [0.0, -2.0], "Q6o": [0.0, -2.0], "K6s": [0.0, -2.0], "K6o": [0.0, -2.0], "77": [1.0, -2.0], "87s": [0.485, -2.0], "87o": [0.0, -2.0], "97s": [0.0, -2.0], "97o": [0.0, -2.0], "T7s": [0.0, -2.0], "T7o": [0.0, -2.0], "J7s": [0.0, -2.0], "J7o": [0.0, -2.0], "Q7s": [0.0, -2.0], "Q7o": [0.0, -2.0], "K7s": [1.0, -2.0], "K7o": [0.0, -2.0], "88": [0.0, -2.0], "98s": [0.384, -2.0], "98o": [0.0, -2.0], "T8s": [1.0, -2.0], "T8o": [0.0, -2.0], "J8s": [0.012, -2.0], "J8o": [0.0, -2.0], "Q8s": [0.042, -2.0], "Q8o": [0.0, -2.0], "K8s": [1.0, -2.0], "K8o": [0.0, -2.0], "99": [0.0, -2.0], "T9s": [1.0, -2.0], "T9o": [0.0, -2.0], "J9s": [0.0, -2.0], "J9o": [0.0, -2.0], "Q9s": [1.0, -2.0], "Q9o": [0.0, -2.0], "K9s": [0.691, -2.0], "K9o": [0.0, -2.0], "TT": [0.0, -2.0], "JTs": [0.012, -2.0], "JTo": [0.0, -2.0], "QTs": [1.0, -2.0], "QTo": [0.031, -2.0], "KTs": [0.0, -2.0], "KTo": [0.682, -2.0], "JJ": [0.056, -2.0], "QJs": [0.543, -2.0], "QJo": [0.86, -2.0], "KJs": [0.0, -2.0], "KJo": [1.0, -2.0], "QQ": [0.0, -2.0], "KQs": [0.0, -2.0], "KQo": [1.0, -2.0], "KK": [0.0, -2.0]},"Call":{"AA": [1.0, 40.35], "A2s": [0.0, -14.09], "A2o": [0.0, -15.56], "A3s": [0.0, -7.53], "A3o": [0.0, -10.72], "A4s": [0.0, -18.17], "A4o": [0.0, -6.5], "A5s": [0.651, 1.05], "A5o": [0.0, -1.41], "A6s": [1.0, 7.2], "A6o": [0.0, -13.68], "A7s": [0.722, 3.94], "A7o": [0.0, -11.17], "A8s": [0.154, -7.92], "A8o": [0.0, -9.83], "A9s": [0.0, -15.48], "A9o": [0.0, -12.89], "ATs": [0.302, -3.43], "ATo": [0.432, -2.48], "AJs": [1.0, 17.28], "AJo": [0.0, -7.76], "AQs": [0.0, -11.62], "AQo": [0.0, -13.49], "AKs": [1.0, 3.93], "AKo": [1.0, 7.18], "22": [0.0, -6.16], "32s": [0.0, 7.65], "32o": [0.0, -16.75], "42s": [0.0, 7.74], "42o": [0.0, -8.62], "52s": [0.0, -1.3], "52o": [0.0, -4.9], "62s": [0.0, -15.3], "62o": [0.0, -13.43], "72s": [0.0, -10.07], "72o": [0.0, -10.11], "82s": [0.0, 4.45], "82o": [0.0, -5.62], "92s": [0.0, -10.67], "92o": [0.0, -11.63], "T2s": [0.0, 21.52], "T2o": [0.0, -12.82], "J2s": [0.0, -11.89], "J2o": [0.0, -3.29], "Q2s": [0.0, -8.78], "Q2o": [0.0, -16.63], "K2s": [0.0, -14.51], "K2o": [0.0, -6.38], "33": [0.0, -6.41], "43s": [0.0, -18.46], "43o": [0.0, -6.17], "53s": [0.0, -3.6], "53o": [0.0, -12.81], "63s": [0.0, 2.68], "63o": [0.0, -5.95], "73s": [0.0, 0.31], "73o": [0.0, -5.52], "83s": [0.0, -15.67], "83o": [0.0, -4.36], "93s": [0.0, -16.13], "93o": [0.0, -7.45], "T3s": [0.0, -1.61], "T3o": [0.0, -10.09], "J3s": [0.0, 14.25], "J3o": [0.0, -15.05], "Q3s": [0.0, -18.89], "Q3o": [0.0, -6.83], "K3s": [0.0, -15.46], "K3o": [0.0, -12.77], "44": [0.0, 0.57], "54s": [0.0, 30.83], "54o": [0.0, 4.09], "64s": [0.0, 8.44], "64o": [0.0, -9.29], "74s": [0.0, 8.65], "74o": [0.0, -0.88], "84s": [0.0, -19.23], "84o": [0.0, -0.08], "94s": [0.0, -3.37], "94o": [0.0, -14.37], "T4s": [0.0, 23.86], "T4o": [0.0, -2.3], "J4s": [0.0, -4.26], "J4o": [0.0, -8.2], "Q4s": [0.0, -19.84], "Q4o": [0.0, -12.54], "K4s": [0.0, -16.75], "K4o": [0.0, -10.89], "55": [0.596, 3.72], "65s": [0.0, -4.58], "65o": [0.0, 1.5], "75s": [0.0, -3.25], "75o": [0.0, -3.74], "85s": [0.0, -4.3], "85o": [0.0, -11.57], "95s": [0.0, -0.93], "95o": [0.0, -10.03], "T5s": [0.0, -8.02], "T5o": [0.0, -8.84], "J5s": [0.0, -9.85], "J5o": [0.0, -4.38], "Q5s": [0.0, -4.11], "Q5o": [0.0, -13.73], "K5s": [0.0, 1.93], "K5o": [0.0, -10.46], "66": [1.0, 9.64], "76s": [0.236, 0.67], "76o": [0.0, 0.89], "86s": [0.0, -2.16], "86o": [0.0, -5.09], "96s": [0.0, 10.1], "96o": [0.0, -5.27], "T6s": [0.0, 14.41], "T6o": [0.0, 1.45], "J6s": [0.0, -6.95], "J6o": [0.0, -11.38], "Q6s": [0.0, 10.3], "Q6o": [0.0, -15.89], "K6s": [0.0, -7.54], "K6o": [0.0, -16.8], "77": [0.0, -5.48], "87s": [0.423, 0.52], "87o": [0.0, 2.72], "97s": [0.0, 0.78], "97o": [0.0, -3.94], "T7s": [0.0, -11.46], "T7o": [0.0, -9.48], "J7s": [0.0, -6.77], "J7o": [0.0, -8.09], "Q7s": [0.0, 1.07], "Q7o": [0.0, -5.81], "K7s": [0.0, -18.17], "K7o": [0.0, -14.55], "88": [1.0, 7.41], "98s": [0.616, 1.13], "98o": [0.0, -12.43], "T8s": [0.0, -10.74], "T8o": [0.0, -7.01], "J8s": [0.047, 4.88], "J8o": [0.0, -1.28], "Q8s": [0.958, 12.61], "Q8o": [0.0, -1.99], "K8s": [0.0, -16.23], "K8o": [0.0, -2.32], "99": [1.0, 17.58], "T9s": [0.0, -10.88], "T9o": [0.0, 1.24], "J9s": [1.0, 27.98], "J9o": [0.0, -10.79], "Q9s": [0.0, -10.42], "Q9o": [0.0, -8.71], "K9s": [0.309, -7.37], "K9o": [0.0, 4.38], "TT": [1.0, 16.9], "JTs": [0.988, 2.96], "JTo": [0.0, 3.73], "QTs": [0.0, -19.02], "QTo": [0.0, -10.75], "KTs": [1.0, 21.44], "KTo": [0.0, -14.67], "JJ": [0.944, 7.27], "QJs": [0.457, -3.14], "QJo": [0.0, -12.32], "KJs": [1.0, 9.23], "KJo": [0.0, -14.18], "QQ": [1.0, 45.09], "KQs": [1.0, 41.17], "KQo": [0.0, -6.95], "KK": [1.0, 27.46]}}