{"Position":"BTN","bb":23.0,"Fold":{"AA": [0.0, 0.0], "A2s": [0.746, 0.0], "A2o": [1.0, 0.0], "A3s": [1.0, 0.0], "A3o": [1.0, 0.0], "A4s": [1.0, 0.0], "A4o": [1.0, 0.0], "A5s": [1.0, 0.0], "A5o": [1.0, 0.0], "A6s": [1.0, 0.0], "A6o": [1.0, 0.0], "A7s": [1.0, 0.0], "A7o": [1.0, 0.0], "A8s": [0.267, 0.0], "A8o": [1.0, 0.0], "A9s": [0.0, 0.0], "A9o": [1.0, 0.0], "ATs": [1.0, 0.0], "ATo": [1.0, 0.0], "AJs": [0.919, 0.0], "AJo": [0.0, 0.0], "AQs": [0.0, 0.0], "AQo": [0.0, 0.0], "AKs": [0.0, 0.0], "AKo": [0.0, 0.0], "22": [1.0, 0.0], "32s": [1.0, 0.0], "32o": [1.0, 0.0], "42s": [1.0, 0.0], "42o": [1.0, 0.0], "52s": [1.0, 0.0], "52o": [1.0, 0.0], "62s": [1.0, 0.0], "62o": [1.0, 0.0], "72s": [1.0, 0.0], "72o": [1.0, 0.0], "82s": [1.0, 0.0], "82o": [1.0, 0.0], "92s": [1.0, 0.0], "92o": [1.0, 0.0], "T2s": [1.0, 0.0], "T2o": [1.0, 0.0], "J2s": [1.0, 0.0], "J2o": [1.0, 0.0], "Q2s": [0.644, 0.0], "Q2o": [1.0, 0.0], "K2s": [1.0, 0.0], "K2o": [1.0, 0.0], "33": [1.0, 0.0], "43s": [1.0, 0.0], "43o": [1.0, 0.0], "53s": [1.0, 0.0], "53o": [1.0, 0.0], "63s": [1.0, 0.0], "63o": [1.0, 0.0], "73s": [1.0, 0.0], "73o": [1.0, 0.0], "83s": [1.0, 0.0], "83o": [1.0, 0.0], "93s": [1.0, 0.0], "93o": [1.0, 0.0], "T3s": [1.0, 0.0], "T3o": [1.0, 0.0], "J3s": [1.0, 0.0], "J3o": [1.0, 0.0], "Q3s": [1.0, 0.0], "Q3o": [1.0, 0.0], "K3s": [1.0, 0.0], "K3o": [1.0, 0.0], "44": [1.0, 0.0], "54s": [1.0, 0.0], "54o": [1.0, 0.0], "64s": [1.0, 0.0], "64o": [1.0, 0.0], "74s": [1.0, 0.0], "74o": [1.0, 0.0], "84s": [1.0, 0.0], "84o": [1.0, 0.0], "94s": [1.0, 0.0], "94o": [1.0, 0.0], "T4s": [1.0, 0.0], "T4o": [1.0, 0.0], "J4s": [0.564, 0.0], "J4o": [1.0, 0.0], "Q4s": [1.0, 0.0], "Q4o": [1.0, 0.0], "K4s": [1.0, 0.0], "K4o": [1.0, 0.0], "55": [0.896, 0.0], "65s": [1.0, 0.0], "65o": [1.0, 0.0], "75s": [1.0, 0.0], "75o": [1.0, 0.0], "85s": [1.0, 0.0], "85o": [1.0, 0.0], "95s": [1.0, 0.0], "95o": [1.0, 0.0], "T5s": [0.64, 0.0], "T5o": [1.0, 0.0], "J5s": [1.0, 0.0], "J5o": [1.0, 0.0], "Q5s": [1.0, 0.0], "Q5o": [1.0, 0.0], "K5s": [1.0, 0.0], "K5o": [1.0, 0.0], "66": [1.0, 0.0], "76s": [0.447, 0.0], "76o": [1.0, 0.0], "86s": [1.0, 0.0], "86o": [1.0, 0.0], "96s": [1.0, 0.0], "96o": [1.0, 0.0], "T6s": [1.0, 0.0], "T6o": [1.0, 0.0], "J6s": [0.898, 0.0], "J6o": [1.0, 0.0], "Q6s": [1.0, 0.0], "Q6o": [1.0, 0.0], "K6s": [1.0, 0.0], "K6o": [1.0, 0.0], "77": [0.551, 0.0], "87s": [1.0, 0.0], "87o": [1.0, 0.0], "97s": [1.0, 0.0], "97o": [1.0, 0.0], "T7s": [1.0, 0.0], "T7o": [1.0, 0.0], "J7s": [1.0, 0.0], "J7o": [1.0, 0.0], "Q7s": [0.305, 0.0], "Q7o": [1.0, 0.0], "K7s": [1.0, 0.0], "K7o": [1.0, 0.0], "88": [0.862, 0.0], "98s": [0.005, 0.0], "98o": [1.0, 0.0], "T8s": [1.0, 0.0], "T8o": [1.0, 0.0], "J8s": [0.546, 0.0], "J8o": [0.675, 0.0], "Q8s": [0.47, 0.0], "Q8o": [1.0, 0.0], "K8s": [1.0, 0.0], "K8o": [1.0, 0.0], "99": [0.0, 0.0], "T9s": [1.0, 0.0], "T9o": [1.0, 0.0], "J9s": [0.896, 0.0], "J9o": [1.0, 0.0], "Q9s": [1.0, 0.0], "Q9o": [1.0, 0.0], "K9s": [0.0, 0.0], "K9o": [1.0, 0.0], "TT": [0.372, 0.0], "JTs": [0.31, 0.0], "JTo": [1.0, 0.0], "QTs": [0.684, 0.0], "QTo": [1.0, 0.0], "KTs": [1.0, 0.0], "KTo": [1.0, 0.0], "JJ": [0.0, 0.0], "QJs": [0.286, 0.0], "QJo": [1.0, 0.0], "KJs": [0.0, 0.0], "KJo": [0.0, 0.0], "QQ": [0.0, 0.0], "KQs": [1.0, 0.0], "KQo": [1.0, 0.0], "KK": [0.0, 0.0]},"Call":{"AA": [1.0, 32.87], "A2s": [0.254, -4.45], "A2o": [0.0, -5.93], "A3s": [0.0, -7.6], "A3o": [0.0, -3.68], "A4s": [0.0, -3.09], "A4o": [0.0, -10.38], "A5s": [0.0, -9.93], "A5o": [0.0, -9.01], "A6s": [0.0, -2.73], "A6o": [0.0, -7.37], "A7s": [0.0, -8.64], "A7o": [0.0, -9.04], "A8s": [0.733, 0.85], "A8o": [0.0, -4.9], "A9s": [1.0, 4.74], "A9o": [0.0, -5.05], "ATs": [0.0, -4.0], "ATo": [0.0, -1.04], "AJs": [0.081, -6.34], "AJo": [1.0, 0.33], "AQs": [1.0, 6.31], "AQo": [1.0, 5.87], "AKs": [1.0, 5.25], "AKo": [1.0, 4.55], "22": [0.0, -12.32], "32s": [0.0, -5.39], "32o": [0.0, -7.75], "42s": [0.0, -3.75], "42o": [0.0, -11.58], "52s": [0.0, -11.91], "52o": [0.0, -13.42], "62s": [0.0, -11.45], "62o": [0.0, -9.98], "72s": [0.0, -5.27], "72o": [0.0, -12.02], "82s": [0.0, -14.8], "82o": [0.0, -10.81], "92s": [0.0, -7.11], "92o": [0.0, -12.87], "T2s": [0.0, -12.8], "T2o": [0.0, -12.14], "J2s": [0.0, -5.3], "J2o": [0.0, -8.08], "Q2s": [0.356, -2.32], "Q2o": [0.0, -10.25], "K2s": [0.0, -3.29], "K2o": [0.0, -8.58], "33": [0.0, -9.04], "43s": [0.0, -8.32], "43o": [0.0, -8.85], "53s": [0.0, -10.38], "53o": [0.0, -14.05], "63s": [0.0, -7.21], "63o": [0.0, -12.6], "73s": [0.0, -6.63], "73o": [0.0, -11.88], "83s": [0.0, -7.35], "83o": [0.0, -14.32], "93s": [0.0, -13.67], "93o": [0.0, -12.83], "T3s": [0.0, -14.57], "T3o": [0.0, -13.25], "J3s": [0.0, -6.76], "J3o": [0.0, -7.32], "Q3s": [0.0, -12.56], "Q3o": [0.0, -10.62], "K3s": [0.0, -5.98], "K3o": [0.0, -8.85], "44": [0.0, -7.08], "54s": [0.0, -13.1], "54o": [0.0, -7.89], "64s": [0.0, -10.73], "64o": [0.0, -8.2], "74s": [0.0, -3.08], "74o": [0.0, -8.71], "84s": [0.0, -18.92], "84o": [0.0, -8.14], "94s": [0.0, -6.28], "94o": [0.0, -8.75], "T4s": [0.0, -9.32], "T4o": [0.0, -11.03], "J4s": [0.436, -0.45], "J4o": [0.0, -13.06], "Q4s": [0.0, -13.01], "Q4o": [0.0, -12.72], "K4s": [0.0, -4.64], "K4o": [0.0, -10.14], "55": [0.104, -2.05], "65s": [0.0, -2.39], "65o": [0.0, -8.64], "75s": [0.0, -10.93], "75o": [0.0, -9.76], "85s": [0.0, -10.59], "85o": [0.0, -10.75], "95s": [0.0, -3.54], "95o": [0.0, -14.56], "T5s": [0.36, -2.72], "T5o": [0.0, -14.57], "J5s": [0.0, -4.86], "J5o": [0.0, -12.55], "Q5s": [0.0, -5.71], "Q5o": [0.0, -8.95], "K5s": [0.0, -4.64], "K5o": [0.0, -5.99], "66": [0.0, -1.98], "76s": [0.553, 0.4], "76o": [0.0, -8.05], "86s": [0.0, -7.51], "86o": [0.0, -7.25], "96s": [0.0, -7.16], "96o": [0.0, -11.82], "T6s": [0.0, -5.7], "T6o": [0.0, -10.3], "J6s": [0.102, -1.69], "J6o": [0.0, -8.05], "Q6s": [0.0, -4.06], "Q6o": [0.0, -11.23], "K6s": [0.0, -4.84], "K6o": [0.0, -8.98], "77": [0.449, -0.63], "87s": [0.0, -5.69], "87o": [0.0, -4.84], "97s": [0.0, -11.61], "97o": [0.0, -5.84], "T7s": [0.0, -4.52], "T7o": [0.0, -8.26], "J7s": [0.0, -8.11], "J7o": [0.0, -11.02], "Q7s": [0.695, 0.77], "Q7o": [0.0, -6.45], "K7s": [0.0, -5.67], "K7o": [0.0, -7.94], "88": [0.138, -3.45], "98s": [0.995, 2.93], "98o": [0.0, -9.66], "T8s": [0.0, -5.75], "T8o": [0.0, -1.59], "J8s": [0.454, -0.49], "J8o": [0.325, -1.94], "Q8s": [0.53, 0.52], "Q8o": [0.0, -8.78], "K8s": [0.0, -2.02], "K8o": [0.0, -5.14], "99": [1.0, 1.57], "T9s": [0.0, -6.32], "T9o": [0.0, -3.6], "J9s": [0.104, -2.38], "J9o": [0.0, -10.42], "Q9s": [0.0, -4.56], "Q9o": [0.0, -6.03], "K9s": [1.0, 3.54], "K9o": [0.0, -5.13], "TT": [0.628, 1.67], "JTs": [0.69, 1.47], "JTo": [0.0, -4.28], "QTs": [0.316, -1.84], "QTo": [0.0, -7.48], "KTs": [0.0, -6.08], "KTo": [0.0, -5.69], "JJ": [1.0, 14.36], "QJs": [0.714, 2.93], "QJo": [0.0, -2.47], "KJs": [1.0, 4.43], "KJo": [1.0, 0.28], "QQ": [1.0, 7.55], "KQs": [0.0, -9.25], "KQo": [0.0, -3.76], "KK": [1.0, 14.6]}}