{"Position":"HJ","bb":23.0,"Fold":{"AA": [0.0, -5.25], "A2s": [0.0, -5.25], "A2o": [0.0, -5.25], "A3s": [0.0, -5.25], "A3o": [0.0, -5.25], "A4s": [0.0, -5.25], "A4o": [0.0, -5.25], "A5s": [0.0, -5.25], "A5o": [0.0, -5.25], "A6s": [0.0, -5.25], "A6o": [0.0, -5.25], "A7s": [0.0, -5.25], "A7o": [0.0, -5.25], "A8s": [0.052, -5.25], "A8o": [0.0, -5.25], "A9s": [1.0, -5.25], "A9o": [0.0, -5.25], "ATs": [1.0, -5.25], "ATo": [0.069, -5.25], "AJs": [1.0, -5.25], "AJo": [0.576, -5.25], "AQs": [0.794, -5.25], "AQo": [0.133, -5.25], "AKs": [1.0, -5.25], "AKo": [0.208, -5.25], "22": [0.0, -5.25], "32s": [0.0, -5.25], "32o": [0.0, -5.25], "42s": [0.0, -5.25], "42o": [0.0, -5.25], "52s": [0.0, -5.25], "52o": [0.0, -5.25], "62s": [0.0, -5.25], "62o": [0.0, -5.25], "72s": [0.0, -5.25], "72o": [0.0, -5.25], "82s": [0.0, -5.25], "82o": [0.0, -5.25], "92s": [0.0, -5.25], "92o": [0.0, -5.25], "T2s": [0.0, -5.25], "T2o": [0.0, -5.25], "J2s": [0.0, -5.25], "J2o": [0.0, -5.25], "Q2s": [0.0, -5.25], "Q2o": [0.0, -5.25], "K2s": [0.0, -5.25], "K2o": [0.0, -5.25], "33": [0.0, -5.25], "43s": [0.0, -5.25], "43o": [0.0, -5.25], "53s": [0.0, -5.25], "53o": [0.0, -5.25], "63s": [0.0, -5.25], "63o": [0.0, -5.25], "73s": [0.0, -5.25], "73o": [0.0, -5.25], "83s": [0.0, -5.25], "83o": [0.0, -5.25], "93s": [0.0, -5.25], "93o": [0.0, -5.25], "T3s": [0.0, -5.25], "T3o": [0.0, -5.25], "J3s": [0.0, -5.25], "J3o": [0.0, -5.25], "Q3s": [0.0, -5.25], "Q3o": [0.0, -5.25], "K3s": [0.0, -5.25], "K3o": [0.0, -5.25], "44": [0.0, -5.25], "54s": [0.0, -5.25], "54o": [0.0, -5.25], "64s": [0.0, -5.25], "64o": [0.0, -5.25], "74s": [0.0, -5.25], "74o": [0.0, -5.25], "84s": [0.0, -5.25], "84o": [0.0, -5.25], "94s": [0.0, -5.25], "94o": [0.0, -5.25], "T4s": [0.0, -5.25], "T4o": [0.0, -5.25], "J4s": [0.0, -5.25], "J4o": [0.0, -5.25], "Q4s": [0.0, -5.25], "Q4o": [0.0, -5.25], "K4s": [0.0, -5.25], "K4o": [0.0, -5.25], "55": [0.0, -5.25], "65s": [0.0, -5.25], "65o": [0.0, -5.25], "75s": [0.0, -5.25], "75o": [0.0, -5.25], "85s": [0.0, -5.25], "85o": [0.0, -5.25], "95s": [0.0, -5.25], "95o": [0.0, -5.25], "T5s": [0.0, -5.25], "T5o": [0.0, -5.25], "J5s": [0.0, -5.25], "J5o": [0.0, -5.25], "Q5s": [0.0, -5.25], "Q5o": [0.0, -5.25], "K5s": [0.0, -5.25], "K5o": [0.0, -5.25], "66": [0.0, -5.25], "76s": [0.0, -5.25], "76o": [0.0, -5.25], "86s": [0.0, -5.25], "86o": [0.0, -5.25], "96s": [0.0, -5.25], "96o": [0.0, -5.25], "T6s": [0.0, -5.25], "T6o": [0.0, -5.25], "J6s": [0.0, -5.25], "J6o": [0.0, -5.25], "Q6s": [0.0, -5.25], "Q6o": [0.0, -5.25], "K6s": [0.0, -5.25], "K6o": [0.0, -5.25], "77": [0.0, -5.25], "87s": [0.0, -5.25], "87o": [0.0, -5.25], "97s": [0.0, -5.25], "97o": [0.0, -5.25], "T7s": [0.0, -5.25], "T7o": [0.0, -5.25], "J7s": [0.0, -5.25], "J7o": [0.0, -5.25], "Q7s": [0.0, -5.25], "Q7o": [0.0, -5.25], "K7s": [0.0, -5.25], "K7o": [0.0, -5.25], "88": [0.939, -5.25], "98s": [0.0, -5.25], "98o": [0.0, -5.25], "T8s": [0.0, -5.25], "T8o": [0.0, -5.25], "J8s": [0.0, -5.25], "J8o": [0.0, -5.25], "Q8s": [0.0, -5.25], "Q8o": [0.0, -5.25], "K8s": [0.0, -5.25], "K8o": [0.0, -5.25], "99": [0.061, -5.25], "T9s": [0.0, -5.25], "T9o": [0.0, -5.25], "J9s": [0.0, -5.25], "J9o": [0.0, -5.25], "Q9s": [0.0, -5.25], "Q9o": [0.0, -5.25], "K9s": [0.0, -5.25], "K9o": [0.0, -5.25], "TT": [0.068, -5.25], "JTs": [0.0, -5.25], "JTo": [0.0, -5.25], "QTs": [0.0, -5.25], "QTo": [0.0, -5.25], "KTs": [0.195, -5.25], "KTo": [0.0, -5.25], "JJ": [0.968, -5.25], "QJs": [0.0, -5.25], "QJo": [0.0, -5.25], "KJs": [0.0, -5.25], "KJo": [0.0, -5.25], "QQ": [1.0, -5.25], "KQs": [0.0, -5.25], "KQo": [0.723, -5.25], "KK": [0.0, -5.25]},"Call":{"AA": [1.0, 27.62], "A2s": [0.0, -8.51], "A2o": [0.0, -11.56], "A3s": [0.0, -8.26], "A3o": [0.0, -11.16], "A4s": [0.0, -7.76], "A4o": [0.0, -10.52], "A5s": [0.0, -7.73], "A5o": [0.0, -10.47], "A6s": [0.0, -8.76], "A6o": [0.0, -11.94], "A7s": [0.0, -8.72], "A7o": [0.0, -11.86], "A8s": [0.0, -8.91], "A8o": [0.0, -12.19], "A9s": [0.0, -9.44], "A9o": [0.0, -12.52], "ATs": [0.0, -8.76], "ATo": [0.0, -12.13], "AJs": [0.0, -9.23], "AJo": [0.0, -12.53], "AQs": [0.0, -9.15], "AQo": [0.0, -12.6], "AKs": [0.0, -5.68], "AKo": [0.0, -8.71], "22": [0.0, -8.48], "32s": [0.0, -9.07], "32o": [0.0, -11.99], "42s": [0.0, -9.21], "42o": [0.0, -11.61], "52s": [0.0, -8.7], "52o": [0.0, -11.25], "62s": [0.0, -9.18], "62o": [0.0, -11.96], "72s": [0.0, -10.65], "72o": [0.0, -13.44], "82s": [0.0, -10.33], "82o": [0.0, -13.31], "92s": [0.0, -10.79], "92o": [0.0, -13.71], "T2s": [0.0, -10.96], "T2o": [0.0, -13.86], "J2s": [0.0, -11.34], "J2o": [0.0, -14.29], "Q2s": [0.0, -11.98], "Q2o": [0.0, -15.18], "K2s": [0.0, -12.09], "K2o": [0.0, -15.43], "33": [0.0, -8.32], "43s": [0.0, -7.36], "43o": [0.0, -10.23], "53s": [0.0, -7.31], "53o": [0.0, -9.97], "63s": [0.0, -7.98], "63o": [0.0, -10.56], "73s": [0.0, -9.36], "73o": [0.0, -12.04], "83s": [0.0, -10.34], "83o": [0.0, -13.29], "93s": [0.0, -10.58], "93o": [0.0, -13.4], "T3s": [0.0, -10.95], "T3o": [0.0, -13.58], "J3s": [0.0, -11.15], "J3o": [0.0, -13.87], "Q3s": [0.0, -11.66], "Q3o": [0.0, -14.66], "K3s": [0.0, -11.75], "K3o": [0.0, -14.98], "44": [0.0, -8.01], "54s": [0.0, -6.07], "54o": [0.0, -8.51], "64s": [0.0, -6.88], "64o": [0.0, -9.34], "74s": [0.0, -8.14], "74o": [0.0, -10.6], "84s": [0.0, -9.07], "84o": [0.0, -11.92], "94s": [0.0, -10.42], "94o": [0.0, -13.45], "T4s": [0.0, -10.2], "T4o": [0.0, -13.3], "J4s": [0.0, -10.88], "J4o": [0.0, -13.58], "Q4s": [0.0, -11.16], "Q4o": [0.0, -14.41], "K4s": [0.0, -11.32], "K4o": [0.0, -14.58], "55": [0.0, -7.84], "65s": [0.0, -5.31], "65o": [0.0, -7.86], "75s": [0.0, -7.01], "75o": [0.0, -9.52], "85s": [0.0, -7.92], "85o": [0.0, -10.77], "95s": [0.0, -9.38], "95o": [0.0, -11.94], "T5s": [0.0, -10.49], "T5o": [0.0, -13.33], "J5s": [0.0, -10.41], "J5o": [0.0, -13.32], "Q5s": [0.0, -11.03], "Q5o": [0.0, -14.13], "K5s": [0.0, -10.93], "K5o": [0.0, -14.32], "66": [0.0, -7.43], "76s": [0.0, -5.9], "76o": [0.0, -8.48], "86s": [0.0, -7.19], "86o": [0.0, -9.65], "96s": [0.0, -8.29], "96o": [0.0, -11.1], "T6s": [0.0, -9.28], "T6o": [0.0, -12.13], "J6s": [0.0, -10.68], "J6o": [0.0, -13.41], "Q6s": [0.0, -10.8], "Q6o": [0.0, -14.13], "K6s": [0.0, -10.93], "K6o": [0.0, -14.35], "77": [0.0, -7.9], "87s": [0.0, -6.61], "87o": [0.0, -9.24], "97s": [0.0, -7.65], "97o": [0.0, -10.24], "T7s": [0.0, -9.02], "T7o": [0.0, -11.45], "J7s": [0.0, -10.03], "J7o": [0.0, -12.63], "Q7s": [0.0, -11.48], "Q7o": [0.0, -14.39], "K7s": [0.0, -11.26], "K7o": [0.0, -14.4], "88": [0.0, -8.11], "98s": [0.0, -7.81], "98o": [0.0, -10.38], "T8s": [0.0, -8.3], "T8o": [0.0, -11.05], "J8s": [0.0, -9.64], "J8o": [0.0, -12.41], "Q8s": [0.0, -10.81], "Q8o": [0.0, -13.84], "K8s": [0.0, -11.65], "K8o": [0.0, -14.67], "99": [0.0, -8.64], "T9s": [0.0, -8.23], "T9o": [0.0, -10.97], "J9s": [0.0, -9.32], "J9o": [0.0, -12.32], "Q9s": [0.0, -10.62], "Q9o": [0.0, -13.71], "K9s": [0.0, -11.69], "K9o": [0.0, -14.79], "TT": [0.0, -8.77], "JTs": [0.0, -9.48], "JTo": [0.0, -12.3], "QTs": [0.0, -10.18], "QTo": [0.0, -13.4], "KTs": [0.0, -11.1], "KTo": [0.0, -14.54], "JJ": [0.0, -8.3], "QJs": [0.0, -10.53], "QJo": [0.0, -13.72], "KJs": [0.0, -11.41], "KJo": [0.0, -14.79], "QQ": [0.0, -6.06], "KQs": [0.0, -11.8], "KQo": [0.0, -15.35], "KK": [1.0, 4.83]}}