{"Position":"BTN","bb":25.0,"Fold":{"AA": [0.0, -83.37], "A2s": [0.0, -86.73], "A2o": [0.0, -86.77], "A3s": [0.0, -86.88], "A3o": [0.0, -86.61], "A4s": [0.0, -86.75], "A4o": [0.0, -86.73], "A5s": [0.0, -87.19], "A5o": [0.0, -87.16], "A6s": [0.0, -87.09], "A6o": [0.0, -86.86], "A7s": [0.0, -87.96], "A7o": [0.0, -87.71], "A8s": [0.0, -87.05], "A8o": [0.0, -86.96], "A9s": [0.23, -86.49], "A9o": [0.0, -86.76], "ATs": [1.0, -86.66], "ATo": [0.0, -87.19], "AJs": [0.0, -87.74], "AJo": [0.273, -87.64], "AQs": [0.222, -88.73], "AQo": [0.0, -88.78], "AKs": [0.0, -85.08], "AKo": [0.0, -85.33], "22": [0.0, -91.07], "32s": [0.0, -90.0], "32o": [0.0, -90.83], "42s": [0.0, -90.98], "42o": [0.0, -90.76], "52s": [0.0, -91.57], "52o": [0.0, -91.38], "62s": [0.0, -90.51], "62o": [0.0, -91.08], "72s": [0.0, -91.52], "72o": [0.0, -91.71], "82s": [0.0, -90.71], "82o": [0.0, -90.87], "92s": [0.0, -90.79], "92o": [0.0, -90.94], "T2s": [0.0, -90.95], "T2o": [0.0, -90.84], "J2s": [0.0, -91.55], "J2o": [0.0, -91.78], "Q2s": [0.0, -93.37], "Q2o": [0.0, -94.32], "K2s": [0.0, -88.77], "K2o": [0.0, -88.59], "33": [0.0, -90.67], "43s": [0.0, -91.01], "43o": [0.0, -91.17], "53s": [0.0, -91.08], "53o": [0.0, -90.98], "63s": [0.0, -91.14], "63o": [0.0, -90.99], "73s": [0.0, -92.3], "73o": [0.0, -91.96], "83s": [0.0, -91.17], "83o": [0.0, -91.38], "93s": [0.0, -90.86], "93o": [0.0, -91.13], "T3s": [0.0, -91.38], "T3o": [0.0, -90.71], "J3s": [0.0, -91.5], "J3o": [0.0, -91.64], "Q3s": [0.0, -94.54], "Q3o": [0.0, -94.22], "K3s": [0.0, -88.13], "K3o": [0.0, -88.68], "44": [0.0, -90.93], "54s": [0.0, -91.0], "54o": [0.0, -91.28], "64s": [0.0, -90.61], "64o": [0.0, -90.88], "74s": [0.0, -92.58], "74o": [0.0, -91.65], "84s": [0.0, -91.27], "84o": [0.0, -90.8], "94s": [0.0, -90.76], "94o": [0.0, -91.14], "T4s": [0.0, -90.72], "T4o": [0.0, -90.72], "J4s": [0.0, -91.6], "J4o": [0.0, -92.36], "Q4s": [0.0, -93.68], "Q4o": [0.0, -93.8], "K4s": [0.0, -88.54], "K4o": [0.0, -88.83], "55": [0.074, -91.46], "65s": [0.0, -91.5], "65o": [0.0, -91.23], "75s": [0.0, -91.57], "75o": [0.0, -92.12], "85s": [0.0, -91.4], "85o": [0.0, -91.45], "95s": [0.0, -91.11], "95o": [0.0, -91.69], "T5s": [0.0, -90.61], "T5o": [0.0, -91.38], "J5s": [0.0, -92.43], "J5o": [0.0, -92.58], "Q5s": [0.0, -94.48], "Q5o": [0.0, -94.56], "K5s": [0.0, -88.28], "K5o": [0.0, -89.0], "66": [0.099, -90.8], "76s": [0.0, -91.69], "76o": [0.0, -91.8], "86s": [0.0, -90.66], "86o": [0.0, -90.8], "96s": [0.0, -91.05], "96o": [0.0, -91.03], "T6s": [0.0, -91.07], "T6o": [0.0, -91.01], "J6s": [0.0, -91.67], "J6o": [0.0, -92.1], "Q6s": [0.0, -93.67], "Q6o": [0.0, -93.93], "K6s": [0.0, -88.86], "K6o": [0.0, -88.55], "77": [0.0, -91.6], "87s": [0.0, -91.96], "87o": [0.0, -91.68], "97s": [0.0, -91.82], "97o": [0.0, -91.83], "T7s": [0.0, -91.66], "T7o": [0.0, -91.56], "J7s": [0.0, -92.29], "J7o": [0.0, -92.58], "Q7s": [0.0, -95.68], "Q7o": [0.0, -95.03], "K7s": [0.0, -89.45], "K7o": [0.0, -89.46], "88": [0.062, -90.65], "98s": [0.0, -91.11], "98o": [0.0, -90.92], "T8s": [0.0, -90.58], "T8o": [0.0, -90.99], "J8s": [0.0, -91.1], "J8o": [0.0, -91.68], "Q8s": [0.0, -93.63], "Q8o": [0.0, -93.96], "K8s": [0.0, -88.47], "K8o": [0.0, -88.69], "99": [0.223, -91.03], "T9s": [0.0, -90.5], "T9o": [0.0, -90.73], "J9s": [0.0, -91.91], "J9o": [0.0, -91.93], "Q9s": [0.0, -93.97], "Q9o": [0.0, -94.25], "K9s": [0.0, -88.6], "K9o": [0.0, -88.75], "TT": [0.236, -90.66], "JTs": [0.0, -91.62], "JTo": [0.0, -91.79], "QTs": [0.0, -93.48], "QTo": [0.0, -94.04], "KTs": [0.145, -88.82], "KTo": [0.0, -88.49], "JJ": [0.078, -92.16], "QJs": [0.0, -95.41], "QJo": [0.0, -95.57], "KJs": [0.0, -89.7], "KJo": [0.0, -89.37], "QQ": [0.0, -97.26], "KQs": [0.0, -90.37], "KQo": [0.112, -90.66], "KK": [0.0, -86.77]},"Call":{"AA": [0.0, 2292.4], "A2s": [0.0, -1433.68], "A2o": [0.0, -1757.48], "A3s": [0.0, -1414.65], "A3o": [0.0, -1708.22], "A4s": [0.0, -1374.28], "A4o": [0.0, -1674.92], "A5s": [0.0, -1312.79], "A5o": [0.0, -1610.07], "A6s": [0.0, -1424.32], "A6o": [0.0, -1720.0], "A7s": [0.0, -1350.55], "A7o": [0.0, -1687.52], "A8s": [0.0, -1377.6], "A8o": [0.0, -1658.66], "A9s": [0.0, -1378.18], "A9o": [0.0, -1679.05], "ATs": [0.0, -1366.59], "ATo": [0.0, -1655.1], "AJs": [0.0, -1320.11], "AJo": [0.0, -1648.68], "AQs": [0.0, -1255.47], "AQo": [0.0, -1580.01], "AKs": [0.0, -664.8], "AKo": [0.0, -929.96], "22": [0.0, -1308.92], "32s": [0.0, -1789.55], "32o": [0.0, -2083.9], "42s": [0.0, -1748.49], "42o": [0.0, -2043.14], "52s": [0.0, -1696.28], "52o": [0.0, -1998.03], "62s": [0.0, -1767.83], "62o": [0.0, -2061.82], "72s": [0.0, -1868.8], "72o": [0.0, -2166.14], "82s": [0.0, -1846.79], "82o": [0.0, -2151.27], "92s": [0.0, -1849.22], "92o": [0.0, -2156.85], "T2s": [0.0, -1892.75], "T2o": [0.0, -2181.56], "J2s": [0.0, -1914.47], "J2o": [0.0, -2239.53], "Q2s": [0.0, -1961.16], "Q2o": [0.0, -2279.76], "K2s": [0.0, -2175.51], "K2o": [0.0, -2518.73], "33": [0.0, -1232.61], "43s": [0.0, -1625.12], "43o": [0.0, -1912.04], "53s": [0.0, -1594.72], "53o": [0.0, -1859.8], "63s": [0.0, -1655.74], "63o": [0.0, -1927.05], "73s": [0.0, -1738.64], "73o": [0.0, -2031.69], "83s": [0.0, -1835.24], "83o": [0.0, -2129.9], "93s": [0.0, -1806.21], "93o": [0.0, -2118.17], "T3s": [0.0, -1860.46], "T3o": [0.0, -2144.24], "J3s": [0.0, -1896.3], "J3o": [0.0, -2183.47], "Q3s": [0.0, -1908.64], "Q3o": [0.0, -2245.66], "K3s": [0.0, -2107.13], "K3o": [0.0, -2469.12], "44": [0.0, -1164.27], "54s": [0.0, -1436.53], "54o": [0.0, -1725.63], "64s": [0.0, -1521.16], "64o": [0.0, -1800.64], "74s": [0.0, -1621.9], "74o": [0.0, -1898.44], "84s": [0.0, -1707.07], "84o": [0.0, -1984.9], "94s": [0.0, -1821.33], "94o": [0.0, -2104.79], "T4s": [0.0, -1792.78], "T4o": [0.0, -2104.15], "J4s": [0.0, -1848.02], "J4o": [0.0, -2131.07], "Q4s": [0.0, -1889.27], "Q4o": [0.0, -2191.14], "K4s": [0.0, -2062.93], "K4o": [0.0, -2416.13], "55": [0.0, -1052.4], "65s": [0.0, -1381.27], "65o": [0.0, -1655.51], "75s": [0.0, -1488.91], "75o": [0.0, -1737.03], "85s": [0.0, -1572.16], "85o": [0.0, -1871.86], "95s": [0.0, -1670.68], "95o": [0.0, -1968.36], "T5s": [0.0, -1800.13], "T5o": [0.0, -2093.71], "J5s": [0.0, -1801.02], "J5o": [0.0, -2095.86], "Q5s": [0.0, -1847.75], "Q5o": [0.0, -2142.18], "K5s": [0.0, -2013.53], "K5o": [0.0, -2361.92], "66": [0.0, -1014.53], "76s": [0.0, -1359.69], "76o": [0.0, -1628.08], "86s": [0.0, -1465.39], "86o": [0.0, -1737.05], "96s": [0.0, -1582.5], "96o": [0.0, -1845.51], "T6s": [0.0, -1685.37], "T6o": [0.0, -1966.96], "J6s": [0.0, -1797.01], "J6o": [0.0, -2089.9], "Q6s": [0.0, -1814.83], "Q6o": [0.0, -2122.06], "K6s": [0.0, -1962.79], "K6o": [0.0, -2323.93], "77": [0.0, -902.24], "87s": [0.0, -1394.08], "87o": [0.0, -1647.47], "97s": [0.0, -1495.63], "97o": [0.0, -1736.92], "T7s": [0.0, -1577.78], "T7o": [0.0, -1859.95], "J7s": [0.0, -1713.9], "J7o": [0.0, -2012.45], "Q7s": [0.0, -1812.5], "Q7o": [0.0, -2143.9], "K7s": [0.0, -1917.05], "K7o": [0.0, -2295.42], "88": [0.0, -810.82], "98s": [0.0, -1445.88], "98o": [0.0, -1703.21], "T8s": [0.0, -1504.54], "T8o": [0.0, -1776.91], "J8s": [0.0, -1636.88], "J8o": [0.0, -1903.44], "Q8s": [0.0, -1730.75], "Q8o": [0.0, -2029.4], "K8s": [0.0, -1933.97], "K8o": [0.0, -2229.09], "99": [0.0, -818.16], "T9s": [0.0, -1457.46], "T9o": [0.0, -1732.21], "J9s": [0.0, -1586.97], "J9o": [0.0, -1856.68], "Q9s": [0.0, -1642.5], "Q9o": [0.0, -1950.26], "K9s": [0.0, -1822.17], "K9o": [0.0, -2188.05], "TT": [0.0, -807.49], "JTs": [0.0, -1564.03], "JTo": [0.0, -1837.09], "QTs": [0.0, -1604.28], "QTo": [0.0, -1924.03], "KTs": [0.0, -1748.88], "KTo": [0.0, -2084.09], "JJ": [0.0, -713.02], "QJs": [0.0, -1653.54], "QJo": [0.0, -1973.85], "KJs": [0.0, -1686.33], "KJo": [0.0, -2001.2], "QQ": [0.0, -176.57], "KQs": [0.0, -1588.89], "KQo": [0.0, -1935.44], "KK": [0.211, 667.05]}}