{"Position":"HJ","bb":25,"Fold":{"AA": [0.0, -0.08], "A2s": [0.0, -0.08], "A2o": [0.0, -0.08], "A3s": [0.0, -0.08], "A3o": [0.0, -0.08], "A4s": [0.0, -0.08], "A4o": [0.0, -0.08], "A5s": [0.046, -0.08], "A5o": [0.0, -0.08], "A6s": [0.0, -0.08], "A6o": [0.0, -0.08], "A7s": [0.003, -0.08], "A7o": [0.0, -0.08], "A8s": [0.458, -0.08], "A8o": [0.0, -0.08], "A9s": [1.0, -0.08], "A9o": [0.0, -0.08], "ATs": [0.835, -0.08], "ATo": [0.124, -0.08], "AJs": [0.0, -0.08], "AJo": [0.43, -0.08], "AQs": [0.0, -0.08], "AQo": [0.0, -0.08], "AKs": [0.0, -0.08], "AKo": [0.0, -0.08], "22": [0.0, -0.08], "32s": [0.0, -0.08], "32o": [0.0, -0.08], "42s": [0.0, -0.08], "42o": [0.0, -0.08], "52s": [0.0, -0.08], "52o": [0.0, -0.08], "62s": [0.0, -0.08], "62o": [0.0, -0.08], "72s": [0.0, -0.08], "72o": [0.0, -0.08], "82s": [0.0, -0.08], "82o": [0.0, -0.08], "92s": [0.0, -0.08], "92o": [0.0, -0.08], "T2s": [0.0, -0.08], "T2o": [0.0, -0.08], "J2s": [0.0, -0.08], "J2o": [0.0, -0.08], "Q2s": [0.0, -0.08], "Q2o": [0.0, -0.08], "K2s": [0.0, -0.08], "K2o": [0.0, -0.08], "33": [0.0, -0.08], "43s": [0.0, -0.08], "43o": [0.0, -0.08], "53s": [0.0, -0.08], "53o": [0.0, -0.08], "63s": [0.0, -0.08], "63o": [0.0, -0.08], "73s": [0.0, -0.08], "73o": [0.0, -0.08], "83s": [0.0, -0.08], "83o": [0.0, -0.08], "93s": [0.0, -0.08], "93o": [0.0, -0.08], "T3s": [0.0, -0.08], "T3o": [0.0, -0.08], "J3s": [0.0, -0.08], "J3o": [0.0, -0.08], "Q3s": [0.0, -0.08], "Q3o": [0.0, -0.08], "K3s": [0.0, -0.08], "K3o": [0.0, -0.08], "44": [0.0, -0.08], "54s": [0.0, -0.08], "54o": [0.0, -0.08], "64s": [0.0, -0.08], "64o": [0.0, -0.08], "74s": [0.0, -0.08], "74o": [0.0, -0.08], "84s": [0.0, -0.08], "84o": [0.0, -0.08], "94s": [0.0, -0.08], "94o": [0.0, -0.08], "T4s": [0.0, -0.08], "T4o": [0.0, -0.08], "J4s": [0.0, -0.08], "J4o": [0.0, -0.08], "Q4s": [0.0, -0.08], "Q4o": [0.0, -0.08], "K4s": [0.0, -0.08], "K4o": [0.0, -0.08], "55": [0.378, -0.08], "65s": [0.0, -0.08], "65o": [0.0, -0.08], "75s": [0.0, -0.08], "75o": [0.0, -0.08], "85s": [0.0, -0.08], "85o": [0.0, -0.08], "95s": [0.0, -0.08], "95o": [0.0, -0.08], "T5s": [0.0, -0.08], "T5o": [0.0, -0.08], "J5s": [0.0, -0.08], "J5o": [0.0, -0.08], "Q5s": [0.0, -0.08], "Q5o": [0.0, -0.08], "K5s": [0.0, -0.08], "K5o": [0.0, -0.08], "66": [0.565, -0.08], "76s": [0.0, -0.08], "76o": [0.0, -0.08], "86s": [0.0, -0.08], "86o": [0.0, -0.08], "96s": [0.0, -0.08], "96o": [0.0, -0.08], "T6s": [0.0, -0.08], "T6o": [0.0, -0.08], "J6s": [0.0, -0.08], "J6o": [0.0, -0.08], "Q6s": [0.0, -0.08], "Q6o": [0.0, -0.08], "K6s": [0.0, -0.08], "K6o": [0.0, -0.08], "77": [0.727, -0.08], "87s": [0.0, -0.08], "87o": [0.0, -0.08], "97s": [0.0, -0.08], "97o": [0.0, -0.08], "T7s": [0.0, -0.08], "T7o": [0.0, -0.08], "J7s": [0.0, -0.08], "J7o": [0.0, -0.08], "Q7s": [0.0, -0.08], "Q7o": [0.0, -0.08], "K7s": [0.0, -0.08], "K7o": [0.0, -0.08], "88": [0.0, -0.08], "98s": [0.0, -0.08], "98o": [0.0, -0.08], "T8s": [0.0, -0.08], "T8o": [0.0, -0.08], "J8s": [0.0, -0.08], "J8o": [0.0, -0.08], "Q8s": [0.0, -0.08], "Q8o": [0.0, -0.08], "K8s": [0.0, -0.08], "K8o": [0.0, -0.08], "99": [0.0, -0.08], "T9s": [0.198, -0.08], "T9o": [0.0, -0.08], "J9s": [0.0, -0.08], "J9o": [0.0, -0.08], "Q9s": [0.0, -0.08], "Q9o": [0.0, -0.08], "K9s": [0.0, -0.08], "K9o": [0.0, -0.08], "TT": [0.0, -0.08], "JTs": [0.511, -0.08], "JTo": [0.0, -0.08], "QTs": [0.505, -0.08], "QTo": [0.0, -0.08], "KTs": [1.0, -0.08], "KTo": [0.0, -0.08], "JJ": [0.0, -0.08], "QJs": [0.643, -0.08], "QJo": [0.0, -0.08], "KJs": [0.014, -0.08], "KJo": [0.0, -0.08], "QQ": [0.0, -0.08], "KQs": [0.0, -0.08], "KQo": [0.335, -0.08], "KK": [0.0, -0.08]},"Call":{"AA": [0.147, 0.76], "A2s": [0.0, -0.19], "A2o": [0.0, -0.26], "A3s": [0.0, -0.18], "A3o": [0.0, -0.25], "A4s": [0.0, -0.18], "A4o": [0.0, -0.25], "A5s": [0.0, -0.16], "A5o": [0.0, -0.24], "A6s": [0.0, -0.18], "A6o": [0.0, -0.26], "A7s": [0.0, -0.18], "A7o": [0.0, -0.25], "A8s": [0.0, -0.17], "A8o": [0.0, -0.24], "A9s": [0.0, -0.13], "A9o": [0.0, -0.2], "ATs": [0.165, -0.08], "ATo": [0.0, -0.14], "AJs": [1.0, -0.02], "AJo": [0.0, -0.08], "AQs": [0.0, 0.1], "AQo": [0.142, 0.05], "AKs": [0.0, 0.24], "AKo": [0.0, 0.2], "22": [0.0, -0.16], "32s": [0.0, -0.36], "32o": [0.0, -0.43], "42s": [0.0, -0.35], "42o": [0.0, -0.42], "52s": [0.0, -0.34], "52o": [0.0, -0.41], "62s": [0.0, -0.36], "62o": [0.0, -0.44], "72s": [0.0, -0.39], "72o": [0.0, -0.47], "82s": [0.0, -0.39], "82o": [0.0, -0.47], "92s": [0.0, -0.38], "92o": [0.0, -0.46], "T2s": [0.0, -0.37], "T2o": [0.0, -0.45], "J2s": [0.0, -0.36], "J2o": [0.0, -0.44], "Q2s": [0.0, -0.32], "Q2o": [0.0, -0.4], "K2s": [0.0, -0.27], "K2o": [0.0, -0.35], "33": [0.0, -0.15], "43s": [0.0, -0.32], "43o": [0.0, -0.4], "53s": [0.0, -0.31], "53o": [0.0, -0.38], "63s": [0.0, -0.33], "63o": [0.0, -0.41], "73s": [0.0, -0.36], "73o": [0.0, -0.44], "83s": [0.0, -0.39], "83o": [0.0, -0.47], "93s": [0.0, -0.37], "93o": [0.0, -0.45], "T3s": [0.0, -0.36], "T3o": [0.0, -0.44], "J3s": [0.0, -0.35], "J3o": [0.0, -0.43], "Q3s": [0.0, -0.32], "Q3o": [0.0, -0.39], "K3s": [0.0, -0.26], "K3o": [0.0, -0.34], "44": [0.0, -0.13], "54s": [0.0, -0.28], "54o": [0.0, -0.35], "64s": [0.0, -0.31], "64o": [0.0, -0.38], "74s": [0.0, -0.34], "74o": [0.0, -0.41], "84s": [0.0, -0.36], "84o": [0.0, -0.44], "94s": [0.0, -0.37], "94o": [0.0, -0.45], "T4s": [0.0, -0.36], "T4o": [0.0, -0.44], "J4s": [0.0, -0.35], "J4o": [0.0, -0.43], "Q4s": [0.0, -0.31], "Q4o": [0.0, -0.39], "K4s": [0.0, -0.26], "K4o": [0.0, -0.33], "55": [0.0, -0.1], "65s": [0.0, -0.28], "65o": [0.0, -0.35], "75s": [0.0, -0.31], "75o": [0.0, -0.38], "85s": [0.0, -0.33], "85o": [0.0, -0.41], "95s": [0.0, -0.34], "95o": [0.0, -0.42], "T5s": [0.0, -0.35], "T5o": [0.0, -0.43], "J5s": [0.0, -0.34], "J5o": [0.0, -0.42], "Q5s": [0.0, -0.3], "Q5o": [0.0, -0.38], "K5s": [0.0, -0.25], "K5o": [0.0, -0.32], "66": [0.072, -0.08], "76s": [0.0, -0.28], "76o": [0.0, -0.35], "86s": [0.0, -0.3], "86o": [0.0, -0.38], "96s": [0.0, -0.31], "96o": [0.0, -0.39], "T6s": [0.0, -0.33], "T6o": [0.0, -0.4], "J6s": [0.0, -0.34], "J6o": [0.0, -0.41], "Q6s": [0.0, -0.29], "Q6o": [0.0, -0.37], "K6s": [0.0, -0.24], "K6o": [0.0, -0.31], "77": [0.012, -0.08], "87s": [0.0, -0.29], "87o": [0.0, -0.36], "97s": [0.0, -0.3], "97o": [0.0, -0.37], "T7s": [0.0, -0.31], "T7o": [0.0, -0.39], "J7s": [0.0, -0.32], "J7o": [0.0, -0.4], "Q7s": [0.0, -0.3], "Q7o": [0.0, -0.38], "K7s": [0.0, -0.24], "K7o": [0.0, -0.32], "88": [0.5, -0.05], "98s": [0.0, -0.29], "98o": [0.0, -0.36], "T8s": [0.0, -0.3], "T8o": [0.0, -0.37], "J8s": [0.0, -0.31], "J8o": [0.0, -0.38], "Q8s": [0.0, -0.29], "Q8o": [0.0, -0.37], "K8s": [0.0, -0.25], "K8o": [0.0, -0.33], "99": [0.022, 0.04], "T9s": [0.0, -0.26], "T9o": [0.0, -0.34], "J9s": [0.0, -0.28], "J9o": [0.0, -0.35], "Q9s": [0.0, -0.26], "Q9o": [0.0, -0.33], "K9s": [0.0, -0.21], "K9o": [0.0, -0.28], "TT": [0.001, 0.15], "JTs": [0.0, -0.23], "JTo": [0.0, -0.3], "QTs": [0.0, -0.2], "QTo": [0.0, -0.27], "KTs": [0.0, -0.14], "KTo": [0.0, -0.21], "JJ": [0.019, 0.27], "QJs": [0.0, -0.18], "QJo": [0.0, -0.25], "KJs": [0.0, -0.12], "KJo": [0.0, -0.18], "QQ": [0.0, 0.43], "KQs": [0.366, -0.06], "KQo": [0.0, -0.12], "KK": [0.074, 0.6]}}